Workbook
Name Bienes_Biomasa_Biogás: Bienes!$A$4:$A$44
Name Bienes_Biomasa_Cultivos_energéticos: Bienes!$D$4:$D$30
Name Bienes_Biomasa_Gasificación: Bienes!$B$4:$B$32
Name Bienes_Biomasa_Generación_cogeneración: Bienes!$E$4:$E$51
Name Bienes_Biomasa_Pirolización: Bienes!$C$4:$C$39
Name Bienes_Eólica_Eólica: Bienes!$F$4:$F$37
Name Bienes_Geotérmica_Central_de_ciclo_binario: Bienes!$I$4:$I$51
Name Bienes_Geotérmica_Central_de_vapor_seco: Bienes!$G$4:$G$51
Name Bienes_Geotérmica_Central_flash: Bienes!$H$4:$H$51
Name Bienes_PCH_Hidráulica: Bienes!$J$4:$J$37
Name Bienes_PCH_Hidrocinética: Bienes!$K$4:$K$37
Name Bienes_Solar_Fotovoltaica: Bienes!$L$4:$L$42
Name NOMBRE: 'FORMATO 1'!$A$34
Name re: 'FORMATO 2'!$F$21
Name REC_Biomasa: Listas2!$F$5:$F$13
Name REC_Eólica: Listas2!$F$20
Name REC_Geotérmica: Listas2!$F$24
Name REC_PCH: Listas2!$F$28
Name REC_Solar: Listas2!$F$32
Name Servicios_Biomasa: Servicios!$A$4:$A$15
Name Servicios_Eólica: Servicios!$B$4:$B$13
Name Servicios_Geotérmica: Servicios!$C$4:$C$18
Name Servicios_PCH: Servicios!$D$4:$D$12
Name Servicios_Solar: Servicios!$E$4:$E$14
Name TEC_Biomasa: Listas2!$H$5:$H$9
Name TEC_Eólica: Listas2!$H$17
Name TEC_Geotérmica: Listas2!$H$22:$H$24
Name TEC_PCH: Listas2!$H$29:$H$30
Name TEC_Solar: Listas2!$H$35

Sheet FORMATO 1
D2: FORMATO SOLICITUD DE INCENTIVOS TRIBUTARIOS PARA PROYECTOS DE FNCE EXCLUSIÓN DE IVA, DEDUCCIÓN EN RENTA EXENCIÓN DE ARANCEL Y DEPRECIACIÓN ACELERADA | Y2: Código: : F-CT-01
Y3: Fecha: 04/12/2024
Y5: Versión: 03
A13: FORMATO 1 FORMATO ÚNICO DE SOLICITUD PARA INCENTIVOS A LA INVERSIÓN EN PROYECTOS DE FNCE (CAPÍTULO III DE LA LEY 1715 DE 2014)
A14: 1. SOLICITANTES
A15: 1.1 Solicitante Principal | P15: 1.2 Solicitante Secundario
A16: Nombre o razón social | P16: Nombre o razón social
A17: SUN FACTORY SAS ESP | P17: Solenium S.A.S
A18: Sector productivo | P18: Sector productivo | V18: Instalaciones Eléctricas
A19: Código CIIU | P19: Código CIIU | V19: 4321 - Instalaciones eléctricas
A20: Rol | P20: Rol | V20: Instalador
A21: C.C ó NIT | P21: C.C ó NIT | V21: 901097244-5
A22: Departamento | P22: Departamento | V22: ANTIOQUIA
A23: Municipio | G23: BOGOTÁ. D.C. | P23: Municipio | V23: MEDELLÍN
A24: Dirección | P24: Dirección | V24: CALLE 46 #70A-79
A25: Teléfono | P25: Teléfono | V25: (+57) 316 1935991
A26: Nombre del Representante Legal (R.L.) | P26: Nombre del Representante Legal (R.L.) | V26: Jaibet Paola Santiago Ribón
A27: C.C o C.E Representante Legal | P27: C.C o C.E Representante Legal | V27: 1152203750
A28: correo electrónico de notificación | P28: correo electrónico de notificación | V28: info@solenium.co
A29: CONTACTO | P29: CONTACTO
A30: Nombre de la persona de contacto | P30: Nombre de la persona de contacto | V30: Sergio Danny Camacho Guzman
A31: Teléfono de la persona de contacto | P31: Teléfono de la persona de contacto | V31: (+57) 301 2950511
A32: Correo Electrónico persona de contacto | P32: Correo Electrónico persona de contacto | V32: tramites@solenium.co
A33: 2. NOMBRE DEL PROYECTO DE FNCE
A34: MGS 0000
A36: 3. ETAPA DEL PROYECTO EN FNCE
A37: Inversión
A38: 4. INFORMACIÓN DE REGISTRO DEL PROYECTO
A39: Número de radicado del registro del proyecto expedido por la UPME (Si aplica) | R39: Fecha del radicado
A40: 5. INCENTIVOS A LOS CUALES APLICA (Marque con una X)
A41: Exclusión de IVA | D41: X | E41: Exención de Arancel | L41: X | M41: Deducción de Renta | T41: X | U41: Depreciación acelerada | AC41: X
A42: 6. LUGAR DE UBICACIÓN DE LA INVERSION
A44: Departamento | F44: Antioquia | P44: Municipio | T44: Titiribí
A46: 7. VALOR DE LA INVERSION OBJETO DEL BENEFICIO ANTES DE IMPUESTOS
A47: Valor total en COP
A48: 8. NÚMERO DE ACREDITACIÓN O REFERENCIA DE PAGO DE LA TARIFA
A49: Número de referencia de pago (CUS)
A50: 9. DECLARACIÓN
A51: Con la presente solicitud declaro que toda la información suministrada con miras a obtener la certificación que permita acceder a los incentivos establecidos en los artículos 11, 12, 13 y 14 de la Ley 1715 de 2014, modificados por la Ley 2099 de 2021, es veraz y me hago responsable por ella. Así mismo, autorizo a la UPME para que de conformidad con el artículo 67 del Código de Procedimiento Administrativo y de lo Contencioso Administrativo, notifique todas las actuaciones surtidas en desarrollo del trámite al correo electrónico de notificaciones informado en el presente documento.
B56: Firma del R.L. del solicitante principal | Q56: Firma del R.L. del solicitante secundario
B57: C.C / C.E | Q57: C.C / C.E | S57: 1152203750

Sheet FORMATO 2
C2: FORMATO SOLICITUD DE INCENTIVOS TRIBUTARIOS PARA PROYECTOS DE FNCE EXCLUSIÓN DE IVA, DEDUCCIÓN EN RENTA EXENCIÓN DE ARANCEL Y DEPRECIACIÓN ACELERADA | T2: Código: F-CT-01
T3: Fecha: 10/10/2024
T5: Versión: 03
A14: FORMATO 2 GENERALIDADES DEL PROYECTO DE FNCE (CAPÍTULO III DE LA LEY 1715 DE 2014)
A16: 1. INFORMACIÓN GENERAL DEL PROYECTO DE FNCE
A17: Nombre del proyecto | F17: =NOMBRE -> MGS 0000
A18: Sector donde se realizará el proyecto | F18: Generación eléctrica
A19: Tipo de generador | F19: Generador
A20: Tipo de FNCE (Ley 1715 de 2014) | F20: Solar
A21: Recurso Energético | F21: Sol
L22: Relacionar Cual
A23: Tecnología | F23: Fotovoltaica
F24: Otra | L24: Relacionar Cual
A25: Ubicación | F25: Departamento
F26: Municipio
F27: Zona | L27: SIN
A28: 2. INFORMACIÓN TÉCNICA
A29: Datos técnicos | F29: Área del Proyecto (m2)
F30: Capacidad Instalada (kW)
F31: Energía Generada (kWh/año)
F32: Vida útil del proyecto (años)
F33: Eficiencia de la planta (%)
F34: Factor de Planta (%)
A35: Datos de Conexión | F35: ¿Se conectará a la red? | N35: Si
F36: Nivel de tensión (kV) (Cuando aplique)
F37: Nombre del Operador de Red (Cuando aplique) | N37: AIR-E
A38: 3. PERIODO DE EJECUCIÓN
A39: Periodo de Ejecución | F39: Fecha estimada de inicio de construcción | N39: 45667
F40: Fecha estimada de entrada en operación comercial
A41: 4. INFORMACIÓN ECONÓMICA
A42: Datos Económicos | F42: Costo total del proyecto antes de IVA (COP)
F43: IVA del proyecto (COP)
F44: Costo de generación sin el proyecto (COP/kWh) (Cuando aplique)
A45: 5. DESCRIPCIÓN DEL PROYECTO

Sheet FORMATO 3
C2: FORMATO SOLICITUD DE INCENTIVOS TRIBUTARIOS PARA PROYECTOS DE FNCE EXCLUSIÓN DE IVA, DEDUCCIÓN EN RENTA EXENCIÓN DE ARANCEL Y DEPRECIACIÓN ACELERADA | M2: Código: F-CT-01
M3: Fecha: 10/10/2024
M5: Versión: 03
A10: FORMATO 3 FORMATO DE ESPECIFICACIONES DE ELEMENTOS, EQUIPOS Y/O MAQUINARIA (CAPÍTULO III DE LA LEY 1715 DE 2014)
A11: Ítem | B11: Nombre del Elemento/Equipo/Maquinaria | C11: Subpartida arancelaria | D11: Cantidad | E11: Unidad de Medida | F11: Marca | G11: Modelo / Referencia | H11: Normas técnicas | I11: Fabricante | J11: Proveedor | K11: Valor total en COP (Sin incluir IVA) | L11: Valor IVA en COP | M11: Función | N11: Soporte | O11: Certificado de Conformidad de Producto | P11: Odoo ID
A12: 1 | B12: Subestación o Power Station | C12: 8504.34.10.00 | D12: 1 | E12: unidades | F12: ZENTRACK | G12: CN-1250/012 | H12: EN61000-6:2019; EN61000-6-4:2019; IEC 61558- 1:2019; IEC 62271-202:2022; IEC 61330:1995 | I12: EAGLERISE ELECTRIC & ELECTRONIC (CHINA) CO. LTD | J12: NEXUS TRADE CONSULTING LIMITED | K12: 577362000 | L12: =K12*0.19 -> 109698780 | M12: La subestación compacta para intemperie transforma la energía generada en baja tensión por el proyecto fotovoltaico a media tensión, permitiendo su integración a la red de distribución local. Cuenta con centros de transformación, celdas de medida y protección, y dispositivos contra sobrecorriente y sobrevoltaje. Su función es esencial para suministrar energía a los habitantes cercanos. | N12: https://drive.google.com/drive/folders/149PiE67rtKaDRx-CQfP_LsUKNH8RPryo | P12: No encontrado
A13: 2 | B13: Subestación o Power Station | C13: 8504.34.10.00 | D13: 1 | E13: unidades | F13: ZENTRACK | G13: CN-1250/015 | H13: EN61000-6:2019; EN61000-6-4:2019; IEC 61558-1:2019; IEC 62271-202:2022; IEC 61330:1995 | I13: EAGLERISE ELECTRIC & ELECTRONIC (CHINA) CO. LTD | J13: NEXUS TRADE CONSULTING LIMITED | K13: 7.1312284e+08 | L13: $135.493.339,59 | M13: La subestación compacta para intemperie transforma la energía generada en baja tensión por el proyecto fotovoltaico a media tensión, permitiendo su integración a la red de distribución local. Cuenta con centros de transformación, celdas de medida y protección, y dispositivos contra sobrecorriente y sobrevoltaje. Su función es esencial para suministrar energía a los habitantes cercanos. | N13: https://drive.google.com/drive/folders/1BZTPlrGbiOcKSSlGhOfzdjAdnugKSXtF | P13: No encontrado
A14: 3 | B14: Subestación o Power Station | C14: 85.04.22.90.00 | D14: 1 | E14: unidades | F14: ZENTRACK | G14: CN-1100/022 | H14: EN61000-6:2019; EN61000-6-4:2019; IEC 61558-1:2019; IEC 62271-202:2022; IEC 61330:1995 | I14: EAGLERISE ELECTRIC & ELECTRONIC (CHINA) CO. LTD | J14: ZENTRACK | K14: 577362000 | L14: =K14*0.19 -> 109698780 | M14: La subestación compacta para intemperie transforma la energía generada en baja tensión por el proyecto fotovoltaico a media tensión, permitiendo su integración a la red de distribución local. Cuenta con centros de transformación, celdas de medida y protección, y dispositivos contra sobrecorriente y sobrevoltaje. Su función es esencial para suministrar energía a los habitantes cercanos. | N14: https://drive.google.com/drive/folders/1cc5cpb9x2xwyAoBBs67LEUqpqbe4cNCu | P14: P01931
A15: 4 | B15: Subestación o Power Station | C15: 85.04.22.90.00 | D15: 1 | E15: unidades | F15: ZENTRACK | G15: CN-1100/025 | H15: EN61000-6:2019; EN61000-6-4:2019; IEC 61558-1:2019; IEC 62271-202:2022; IEC 61330:1995 | I15: EAGLERISE ELECTRIC & ELECTRONIC (CHINA) CO. LTD | J15: ZENTRACK | K15: 593808411 | L15: =K15*0.19 -> 1.128236e+08 | M15: La subestación compacta para intemperie transforma la energía generada en baja tensión por el proyecto fotovoltaico a media tensión, permitiendo su integración a la red de distribución local. Cuenta con centros de transformación, celdas de medida y protección, y dispositivos contra sobrecorriente y sobrevoltaje. Su función es esencial para suministrar energía a los habitantes cercanos. | N15: https://drive.google.com/drive/folders/184IyEgfQEVb0mxUHFCwhbcytQbdnM25v | P15: No encontrado
A16: 5 | B16: Seguidores solares | C16: 7308.90.90.00 | D16: 18 | E16: unidades | F16: ZENTRACK | G16: Tracker 1P Singsun | H16: ISO 9001, ISO 14001, ISO 1461 | I16: JIANGSU GUOQIANG SINGSUN ENERGY CO., LTD | J16: ZENTRACK | K16: =K14*0.85 -> 490757700 | L16: =K16*0.19 -> 93243963 | M16: Estructura móvil instalada para soportar los módulos fotovoltaicos y para seguir la trayectoria del sol. | N16: https://drive.google.com/drive/folders/13HHTDddZaBxA5miHhexjxiByePe9BqxS | P16: P00575
A17: 6 | B17: Seguidores solares | C17: 7308.90.90.00 | D17: 18 | E17: unidades | F17: ZENTRACK | G17: Tracker 2P Singsun | H17: ISO 9001, ISO 14001, ISO 1461 | I17: JIANGSU GUOQIANG SINGSUN ENERGY CO., LTD | J17: ZENTRACK | K17: =K15*0.85 -> 5.0473715e+08 | L17: =K17*0.19 -> 95900058 | M17: Estructura móvil instalada para soportar los módulos fotovoltaicos y para seguir la trayectoria del sol. | N17: https://drive.google.com/drive/folders/1LGlr0snTHTDmlIvybUh5fmdkNjI15f5y | P17: P00576
A18: 7 | B18: Unidad funcional | C18: 8479.89.90.00 | D18: 20 | E18: unidades | F18: TrinaTracker | G18: Vanguard -2P | H18: UL 3703, UL 2703, IEC 62817, ISO 9001, ISO14001 | I18: Trina Solar Co.,Ltd | J18: Trina Solar Co.,Ltd | K18: 500428320 | L18: =K18*0.19 -> 95081381 | M18: Soporte estructural para los paneles solares con un sistema de "tracking" que le permite girar sobre su eje transversal para seguir el sol, el equipo fue clasificado arancelariamente como una unidad funcional por la Dirección de Impuestos y Aduanas Nacionales | N18: https://drive.google.com/drive/folders/13R5ydcDZsTgU9S9CVxafW9PKXeEsitjV?usp=drive_link | P18: P00576
A19: 8 | B19: Unidad funcional | C19: 8479.89.90.00 | D19: 20 | E19: unidades | F19: Zentrack | G19: Tracker 1P Singsun | H19: ISO 9001, ISO 14001, ISO 1461 | I19: JIANGSU GUOQIANG SINGSUN ENERGY CO., LTD | J19: ZENTRACK | K19: =K17*0.85 -> 4.2902658e+08 | L19: =K19*0.19 -> 81515050 | M19: Soporte estructural para los paneles solares con un sistema de "tracking" que le permite girar sobre su eje transversal para seguir el sol, el equipo fue clasificado arancelariamente como una unidad funcional por la Dirección de Impuestos y Aduanas Nacionales | N19: https://drive.google.com/drive/folders/1rzFaWfqPq962WWIfcZTMSwxV9pyxXJao | P19: P00575
A20: 9 | B20: Sistema de monitoreo, control y automatización | C20: 9032.89.90.00 | D20: 19 | E20: unidades | F20: ZENTRACK | G20: CONTROLADOR SEGUIDOR SOLAR V1R3 | H20: ISO 9001 UL (E332411) | I20: H.C.C. International Limited | J20: ZENTRACK SAS | K20: =K12*0.15 -> 86604300 | L20: =K20*0.19 -> 16454817 | M20: Controladores Zentrack, estos equipos se encargan de realizar el control de los motores utilizados para posicionar en posición perpendicular al sol el seguidor solar que soporta los paneles solares. El controlador calcula la trayectoria del sol y con un sensor de inclinación integrado posiciona la estructura para seguir el sol. Hace parte esencial del sistema de seguimiento solar | N20: https://drive.google.com/drive/folders/1rzFaWfqPq962WWIfcZTMSwxV9pyxXJao | P20: No encontrado
A21: 10 | B21: Paneles/modulos o celdas fotovoltaicas | C21: 8541.43.00.00 | D21: 994 | E21: unidades | F21: LONGi | G21: LR5-72HGD-580M | H21: IEC61215, IEC61730, UL61730, IEC62941 | I21: LONGi | J21: LONGi | K21: 1.1081705e+09 | L21: =0 -> 0 | M21: Principal componente del sistema de energía solar y su función es transformar la radiación solar directamente en electricidad | N21: https://drive.google.com/drive/folders/1v5PFo_rL5WEAQ9DsjzwtKHaQqFWCfoNn | P21: P00771
A22: 11 | B22: Paneles/modulos o celdas fotovoltaicas | C22: 8541.43.00.00 | D22: 2206 | E22: unidades | F22: LONGi | G22: LR7-72HGD610M | H22: IEC61215, IEC61730, UL61730, IEC62941 | I22: LONGi | J22: LONGi | K22: 1.1081705e+09 | L22: =0 -> 0 | M22: Principal componente del sistema de energía solar y su función es transformar la radiación solar directamente en electricidad | N22: https://drive.google.com/drive/folders/1W0chWWJxQITFQX8qZPlnjboQTzuztD1F | P22: P01666
A23: 12 | B23: Paneles/modulos o celdas fotovoltaicas | C23: 8541.43.00.00 | D23: 2032 | E23: unidades | F23: LONGi | G23: LR7-72HYD-650M | H23: IEC61215, IEC61730, UL61730, IEC62941 | I23: LONGi | J23: LONGi | K23: 1.1081705e+09 | L23: =0 -> 0 | M23: Principal componente del sistema de energía solar y su función es transformar la radiación solar directamente en electricidad | N23: https://drive.google.com/drive/folders/1Xzeum8R9QMY_Y8iTd8-rQO30BLzR3Cru | P23: P00773
A24: 13 | B24: Paneles/modulos o celdas fotovoltaicas | C24: 8541.43.00.00 | D24: 2196 | E24: unidades | F24: LONGi | G24: LR7-72HGD-615M | H24: IEC61215, IEC61730, UL61730, IEC62941 | I24: LONGi | J24: LONGi | K24: 1.1081705e+09 | L24: =0 -> 0 | M24: Principal componente del sistema de energía solar y su función es transformar la radiación solar directamente en electricidad | N24: https://drive.google.com/drive/folders/1W0chWWJxQITFQX8qZPlnjboQTzuztD1F | P24: P01526
A25: 14 | B25: Paneles/modulos o celdas fotovoltaicas | C25: 8541.43.00.00 | D25: 2032 | E25: unidades | F25: LONGi | G25: LR8-66HVD-655M | H25: IEC61215, IEC61730, UL61730, IEC62941 | I25: LONGi | J25: LONGi | K25: 1.1081705e+09 | L25: =0 -> 0 | M25: Principal componente del sistema de energía solar y su función es transformar la radiación solar directamente en electricidad | N25: https://drive.google.com/drive/folders/19efuYBKjM8Oh-ZfVDbMFTiX1XJq4P8ez | P25: P01667
A26: 15 | B26: Paneles/modulos o celdas fotovoltaicas | C26: 8541.43.00.00 | D26: 2032 | E26: unidades | F26: LONGi | G26: LR8-66HGD-615M | H26: IEC61215, IEC61730, UL61730, IEC62941 | I26: LONGi | J26: LONGi | K26: 1.1081705e+09 | L26: =0 -> 0 | M26: Principal componente del sistema de energía solar y su función es transformar la radiación solar directamente en electricidad | N26: https://drive.google.com/drive/folders/14zrIbdPCsxdJuhHTGBpgY2jL9lzFebsN | P26: P01526
A27: 16 | B27: Paneles/modulos o celdas fotovoltaicas | C27: 8541.43.00.00 | D27: 2032 | E27: unidades | F27: LONGi | G27: LR8-66HYD-655M | H27: IEC61215, IEC61730, UL61730, IEC62941 | I27: LONGi | J27: LONGi | K27: 1.1081705e+09 | L27: =0 -> 0 | M27: Principal componente del sistema de energía solar y su función es transformar la radiación solar directamente en electricidad | N27: https://drive.google.com/drive/folders/1rsZFZeulPRCYwiMXlaM-GcvB3vIGGO3x | P27: P01667
A28: 17 | B28: Paneles/modulos o celdas fotovoltaicas | C28: 8541.43.00.00 | D28: 2032 | E28: unidades | F28: LONGi | G28: LR7-72HGD 620M | H28: IEC61215, IEC61730, UL61730, IEC62941 | I28: LONGi | J28: LONGi | K28: 1.1081705e+09 | L28: =0 -> 0 | M28: Principal componente del sistema de energía solar y su función es transformar la radiación solar directamente en electricidad | N28: https://drive.google.com/drive/folders/1W0chWWJxQITFQX8qZPlnjboQTzuztD1F | P28: P01527
A29: 18 | B29: Inversores o microinversores (Off Gid, Grid Tie o Híbrido) | C29: 8504409090 | D29: 4 | E29: unidades | F29: Huawei | G29: SUN2000-247.5KTL-H1 | H29: IEC 61727:2004; IEC 62116:2014 | I29: Huawei Technologies Co., Ltd. | J29: HUAWEI INTERNATIONAL CO LIMITED | K29: 1.0355318e+08 | L29: 19675105 | M29: Transformacion de energia DC/AC | N29: https://drive.google.com/drive/folders/1uzr6NJKRStMhnDDofeFaPjLjh0KdD8f5 | O29: https://drive.google.com/drive/folders/1RRBxfJPuzZMLRVIzMTb4NSErLaOxCt5w | P29: P01243
A30: 19 | B30: Inversores o microinversores (Off Gid, Grid Tie o Híbrido) | C30: 8504409090 | D30: 4 | E30: unidades | F30: Huawei | G30: SUN2000-249KTL-H1 | H30: IEC 61727:2004; IEC 62116:2014 | I30: Huawei Technologies Co., Ltd. | J30: HUAWEI INTERNATIONAL CO LIMITED | K30: 1.0355318e+08 | L30: 19675105 | M30: Transformacion de energia DC/AC | N30: https://drive.google.com/drive/folders/1IYQfLVwNswfcGO-dKZOEcPAWXMJShUL_ | O30: https://drive.google.com/drive/folders/1RRBxfJPuzZMLRVIzMTb4NSErLaOxCt5w | P30: P01243
A31: 20 | B31: Inversores o microinversores (Off Gid, Grid Tie o Híbrido) | C31: 8504409090 | D31: 3 | E31: Unidades | F31: Huawei | G31: SUN2000-330KTL-H1 | H31: IEC 61727:2004 Photovoltaic (PV) systems – Characteristics of the utility interface IEC 62116:2014 Test procedure of islanding prevention measures for utilityinterconnected photovoltaic inverters | I31: Huawei Technologies Co., Ltd. | J31: HUAWEI INTERNATIONAL CO LIMITED | K31: 100730645 | L31: =K31*0.19 -> 19138823 | M31: Transformación de energía DC/AC | N31: https://drive.google.com/drive/folders/1XVHXVNZhsQLqJm55cowRAr7WgAyCuGG9 | P31: P00655
A32: 21 | B32: Inversores o microinversores (Off Gid, Grid Tie o Híbrido) | C32: 8504409090 | D32: 1 | E32: unidades | F32: Huawei | G32: SUN2000-40KTL-M3 | H32: EN 62109-1/-2, IEC 62109-1/-2, EN 50530, IEC 62116, IEC 60068, IEC 61683 | I32: Huawei Technologies Co., Ltd. | J32: HUAWEI INTERNATIONAL CO LIMITED | K32: 10190450 | L32: =K32*0.19 -> 1936185.5 | M32: Transformación de energía DC/AC | N32: https://drive.google.com/drive/folders/1aYvYiIGK0bLmaslxX5eWDsY5gIgAxGE5 | P32: P00656
A33: 22 | B33: Inversores o microinversores (Off Gid, Grid Tie o Híbrido) | C33: 8504409090 | D33: 1 | E33: Unidades | F33: Huawei | G33: SUN2000-50KTL-M3 | H33: EN 62109-1/-2, IEC 62109-1/-2, EN 50530, IEC 62116, IEC 60068, IEC 61683, IEC 61727, ABNT NBR 16149, ABNT NBR 16150, ABNT NBR IEC 62116 | I33: Huawei Technologies Co., Ltd. | J33: HUAWEI INTERNATIONAL CO LIMITED | K33: 12504680 | L33: =K33*0.19 -> 2375889.2 | M33: Transformación de energía DC/AC | N33: https://drive.google.com/drive/folders/1u2EMBQNnKkj1JWL4zsJCQgYfEQb8s4QG | P33: P00657
A34: 23 | B34: Datalogger | C34: 851762200 | D34: 1 | E34: unidad | F34: Huawei | G34: SmartLogger3000A01AU | H34: IEC 60870-5-104, IEC 60870-5-103 | I34: Huawei Technologies Co., Ltd. | J34: HUAWEI INTERNATIONAL CO LIMITED | M34: Datalogger para la supervisión, control y adquisición de datos del sistema fotovoltaico, necesario para la integración con sistemas de monitoreo y cumplimiento de protocolos de comunicación exigidos (IEC 60870-5-104 / 103), permitiendo la gestión de inversores y operación remota del sistema | N34: https://drive.google.com/drive/folders/17nqi9n1BchtoHKfbCfSFiqh2-gNWBx-3 | P34: P01775
A35: 24 | B35: Datalogger | C35: 851762200 | D35: 1 | E35: unidad | F35: Huawei | G35: SmartLogger3000A03EU | H35: IEC 60870-5-104, IEC 60870-5-103 | I35: Huawei Technologies Co., Ltd. | J35: HUAWEI INTERNATIONAL CO LIMITED | M35: Datalogger para la supervisión, control y adquisición de datos del sistema fotovoltaico, necesario para la integración con sistemas de monitoreo y cumplimiento de protocolos de comunicación exigidos (IEC 60870-5-104 / 103), permitiendo la gestión de inversores y operación remota del sistema | N35: https://drive.google.com/drive/folders/17nqi9n1BchtoHKfbCfSFiqh2-gNWBx-3 | P35: P01910
A36: 25 | B36: Conectores MC4 | D36: 200 | E36: unidades | F36: Weidmüller | G36: BUGH WM4 C BT | H36: DIN EN 50521, IEC 62852 | I36: Weidmüller Interface GmbH & Co. KG | J36: Weidmüller Interface GmbH & Co. KG | M36: Conectores que facilitan la conexión de los paneles fotovoltaicos | N36: https://drive.google.com/drive/folders/1-2SDtnilKVkzbzm9670h4Q6m2h67DLEr | P36: P00458
A37: 26 | B37: Conectores MC4 | D37: 200 | E37: unidades | F37: Weidmüller | G37: BUKO WM4 C BT | H37: DIN EN 50521 | I37: Weidmüller Interface GmbH & Co. KG | J37: Weidmüller Interface GmbH & Co. KG | M37: Conectores que facilitan la conexión de los paneles fotovoltaicos | N37: https://drive.google.com/drive/folders/1amUHJ6EEV4uoBb1yKnPdglVV4cfaXurS | P37: P00806
A38: 27 | B38: Conectores MC4 | D38: 200 | E38: unidades | F38: Weidmüller | G38: SFGH WM4 C BT | H38: DIN EN 50521, IEC 62852 | I38: Weidmüller Interface GmbH & Co. KG | J38: Weidmüller Interface GmbH & Co. KG | M38: Conectores que facilitan la conexión de los paneles fotovoltaicos | N38: https://drive.google.com/drive/folders/1OJ3kxVxw9yhyVvPcj4lAtZVRvI6UtXs_ | P38: P00461
A39: 28 | B39: Conectores MC4 | D39: 200 | E39: unidades | F39: Weidmüller | G39: SFkO WM4 C BT | H39: DIN EN 50521 | I39: Weidmüller Interface GmbH & Co. KG | J39: Weidmüller Interface GmbH & Co. KG | M39: Conectores que facilitan la conexión de los paneles fotovoltaicos | N39: https://drive.google.com/drive/folders/1Fp0aiedr33njv9LVd2JC0tg1MAvEB5L_ | P39: P00807
A40: 29 | B40: Interruptores, reconectadores, seccionadores y transferencias automáticas | D40: 1 | E40: Unidad | F40: Noja | G40: OSM-15-12-630 | H40: ANSI C37.60-2012, IEC 61850, IEC 60870-5-101, IEC 60870-5-104, DNP3, IEC 61499, IEC 255, IP66, IP65 | I40: Noja Power Switchgear Pty. Ltd. | J40: Potencia y Tecnologías Incorporadas S.A.S | M40: Equipo encargado de proteger el sistema de generación en media tensión | N40: https://drive.google.com/drive/folders/1Z1p6iVbf8ZfNUNKctMlV-gTfT9a90dUO | P40: P00836
A41: 30 | B41: Interruptores, reconectadores, seccionadores y transferencias automáticas | D41: 1 | E41: Unidad | F41: Noja | G41: OSM27 | H41: ANSI C37.60-2012, IEC 61850, IEC 60870-5-101, IEC 60870-5-104, DNP3, IEC 61499, IEC 255, IP66, IP65 | I41: Noja Power Switchgear Pty. Ltd. | J41: Potencia y Tecnologías Incorporadas S.A.S | M41: Equipo encargado de proteger el sistema de generación en media tensión | N41: https://drive.google.com/drive/folders/1Z1p6iVbf8ZfNUNKctMlV-gTfT9a90dUO | P41: No encontrado
A42: 31 | B42: Interruptores, reconectadores, seccionadores y transferencias automáticas | D42: 1 | E42: Unidad | F42: Noja | G42: OSM38 | H42: ANSI C37.60-2012, IEC 61850, IEC 60870-5-101, IEC 60870-5-104, DNP3, IEC 61499, IEC 255, IP66, IP65 | I42: Noja Power Switchgear Pty. Ltd. | J42: Potencia y Tecnologías Incorporadas S.A.S | M42: Equipo encargado de proteger el sistema de generación en media tensión | N42: https://drive.google.com/drive/folders/1Z1p6iVbf8ZfNUNKctMlV-gTfT9a90dUO | P42: No encontrado
A43: 32 | B43: Interruptores, reconectadores, seccionadores y transferencias automáticas | D43: 1 | E43: Unidad | F43: ABB | G43: OVR-15 | H43: IEC 62271-111 / IEEE C37.60:2012; IEC C37.100.1-2007 | I43: ABB India Limited | J43: ABB | M43: Equipo de protección, maniobra y reconexión automática en redes eléctricas de media tensión. Permite interrumpir corrientes de falla, realizar secuencias de apertura y recierre, proteger la red de distribución y mejorar la continuidad y confiabilidad del sistema eléctrico asociado al proyecto. | N43: https://drive.google.com/drive/folders/130FN_7LTt8PzogdEZa6eTOhOl920Wfrj | P43: P01774
A44: 33 | B44: Interruptores, reconectadores, seccionadores y transferencias automáticas | D44: 1 | E44: Unidad | F44: ABB | G44: OVR-27 | H44: IEC 62271-111 / IEEE C37.60:2012; IEC C37.100.1-2007 | I44: ABB India Limited | J44: ABB | M44: Equipo de protección, maniobra y reconexión automática en redes eléctricas de media tensión. Permite interrumpir corrientes de falla, realizar secuencias de apertura y recierre, proteger la red de distribución y mejorar la continuidad y confiabilidad del sistema eléctrico asociado al proyecto. | N44: https://drive.google.com/drive/folders/130FN_7LTt8PzogdEZa6eTOhOl920Wfrj | P44: No encontrado
A45: 34 | B45: Interruptores, reconectadores, seccionadores y transferencias automáticas | D45: 1 | E45: Unidad | F45: ABB | G45: OVR-38 | H45: IEC 62271-111 / IEEE C37.60:2012; IEC C37.100.1-2007 | I45: ABB India Limited | J45: ABB | M45: Equipo de protección, maniobra y reconexión automática en redes eléctricas de media tensión. Permite interrumpir corrientes de falla, realizar secuencias de apertura y recierre, proteger la red de distribución y mejorar la continuidad y confiabilidad del sistema eléctrico asociado al proyecto. | N45: https://drive.google.com/drive/folders/130FN_7LTt8PzogdEZa6eTOhOl920Wfrj | P45: P01773
A46: 35 | B46: Interruptores, reconectadores, seccionadores y transferencias automáticas | D46: 1 | E46: unidad | F46: ROCKWILL | G46: RCW15/630, Corriente Nominal Cortocircuito 15 kA. | H46: IEC 62271-200:2021, IEC 61439-3:2012, IEC 61439-1:2020, UL 969:2023, IEC 60695-11-10:2013 | I46: Wenzhou Rockwill Electric Co., Ltd | J46: ACOVIS Ingeníeria De Colombia SAS | M46: Equipo encargado de proteger el sistema de generación en media tensión | N46: https://drive.google.com/drive/folders/1WQcos9JHcWphjLlluEt1u6QqWwPv16T6 | P46: P00837
A47: 36 | B47: Interruptores, reconectadores, seccionadores y transferencias automáticas | D47: 1 | E47: unidad | F47: ROCKWILL | G47: RCW38/630 Corriente Nominal Cortocircuito 15 kA. | H47: IEC 62271-200:2021, IEC 61439-3:2012, IEC 61439-1:2020, UL 969:2023, IEC 60695-11-10:2013 | I47: Wenzhou Rockwill Electric Co., Ltd | J47: ACOVIS Ingeníeria De Colombia SAS | M47: Equipo encargado de proteger el sistema de generación en media tensión | N47: https://drive.google.com/drive/folders/1WQcos9JHcWphjLlluEt1u6QqWwPv16T6 | P47: No encontrado
A48: 37 | B48: Interruptores, reconectadores, seccionadores y transferencias automáticas | F48: ROCKWILL | G48: RCW27/630 | H48: IEC 62271-200:2021, IEC 61439-3:2012, IEC 61439-1:2020, UL 969:2023, IEC 60695-11-10:2013 | I48: Wenzhou Rockwill Electric Co., Ltd | J48: ACOVIS Ingeníeria De Colombia SAS | M48: Equipo encargado de proteger el sistema de generación en media tensión | N48: https://drive.google.com/drive/folders/1WQcos9JHcWphjLlluEt1u6QqWwPv16T6 | P48: No encontrado
A49: 38 | B49: Medidores bidireccionales | D49: 2 | E49: unidades | F49: ISKRA | G49: MT880, Medidor trifásico multitarifa | H49: IEC 62052-11-2003,IEC 62053-22/2003, IEC 62053-23/2003 | I49: ISKRAEMECO D.D. | J49: INDUSTRIA ELECTRICA DEL CAUCA S.A.S. - INELCA S.A.S. | M49: Equipo de medida para registrar la energía generada por el sistema y que se inyecta a la red en media tensión | N49: https://drive.google.com/drive/folders/142PceXJfvcSHBq42bMrcYZ0T8zoGQkbR | P49: P00707
A50: 39 | B50: Medidores Inteligentes | E50: Unidades | F50: METCOM Solutions | G50: MCS301 | H50: EN 50470-3; IEC 62053-21; IEC 62053-22; IEC 62052-11; EN 50407-1; EN 62054; IEC 62053-31; EN 62056-21; DIN 43857 parte 2; DIN 43859; DLMS/COSEM; IDIS paquete 2; IP54; MID M1; MID E2. | I50: METCOM Solutions | M50: Medición inteligente de energía eléctrica activa bidireccional, energía reactiva en los 4 cuadrantes, energía aparente, máxima demanda, perfiles de facturación, calidad de energía, armónicos, THD, eventos, comunicación remota y funciones antifraude para segmentos residencial, comercial, industrial y puntos de frontera. | N50: https://drive.google.com/drive/folders/19CYDdqWguMc87HwvJqG6ls0_1yVbusJk | P50: No encontrado
A51: 40 | B51: Medidores Inteligentes | E51: Unidades | F51: METCOM Solutions | G51: MCS301-002-ES | H51: EN 50470-3; IEC 62053-21; IEC 62053-22; IEC 62052-11; EN 50407-1; EN 62054; IEC 62053-31; EN 62056-21; DIN 43857 parte 2; DIN 43859; DLMS/COSEM; IDIS paquete 2; IP54; MID M1; MID E2. | I51: METCOM Solutions | M51: Medición inteligente de energía eléctrica activa bidireccional, energía reactiva en los 4 cuadrantes, energía aparente, máxima demanda, perfiles de facturación, calidad de energía, armónicos, THD, eventos, comunicación remota y funciones antifraude para segmentos residencial, comercial, industrial y puntos de frontera. | N51: https://drive.google.com/drive/folders/19CYDdqWguMc87HwvJqG6ls0_1yVbusJk | P51: No encontrado
A52: 41 | B52: Transformadores (de potencia, medida e instrumentación) | D52: 5 | E52: unidades | F52: Rymel | G52: TCEM 50/5 Clase Medición 0.5s Burden Nominal 5 VA" | H52: IEC61869-2, NTC5933, NTC2205 | I52: Rymel S.A.S. | J52: Rymel S.A.S. | M52: Su principal función es transformar la corriente y aislar los instrumentos de protección y medición conectados a los circuitos de media tensión | N52: https://drive.google.com/drive/folders/1rg2fKpw96CeTPlhwxBy9lKUmkBluhuSD | P52: P01040
A53: 42 | B53: Transformadores (de potencia, medida e instrumentación) | D53: 3 | E53: unidades | F53: ESITAS | G53: ATH 30-N Clase Medición 0.5s Burden Nominal 5 VA | H53: IEC61869-2, NTC5933, NTC2205 | I53: ESITAS | J53: Latam Ifer S.A.S | M53: Su principal función es transformar la corriente y aislar los instrumentos de protección y medición conectados a los circuitos de media tensión | N53: https://drive.google.com/drive/folders/1OsuQpqPHBUB_kOYJ3FmLaR4JtacmLQk- | P53: No encontrado
A54: 43 | B54: Transformadores (de potencia, medida e instrumentación) | D54: 3 | E54: Unidades | F54: ESITAS | G54: VTH 30-N | H54: IEC61869-3, NTC5933, NTC2207 | I54: ESITAS | J54: Latam Ifer S.A.S | M54: Su principal función es transformar la tensión y aislar los instrumentos de protección y medición conectados a los circuitos de media tensión | N54: https://drive.google.com/drive/folders/1zfK8iusdA9tBDpVodUvhgzm_uIYKWr-w | P54: No encontrado
A55: 44 | B55: Transformadores (de potencia, medida e instrumentación) | D55: 5 | E55: unidades | F55: Rymel | G55: TPEM1 13.8/√3 - 120/√3 Clase Medición 0.5 Burden Nominal 5 VA | H55: IEC61869-3, NTC5933, NTC2207 | I55: Rymel S.A.S. | J55: Rymel S.A.S. | M55: Su principal función es transformar la tensión y aislar los instrumentos de protección y medición conectados a los circuitos de media tensión | N55: https://drive.google.com/drive/folders/1rg2fKpw96CeTPlhwxBy9lKUmkBluhuSD | P55: P01851
A56: 45 | B56: Tableros de baja tensión AC/DC (Incluye los elementos internos) | D56: 1 | E56: unidades | F56: TODO LÁMINAS C.E. | G56: TMI (2) - 100 A- 10 kA - IP 44 - 60,70,25 - septiembre 2023 | H56: Numeral 20.23-1 del Reglamento Técnico de Instalaciones Eléctricas - RETIE. Resolución 90708 del 30 de agosto de 2013 y 90795 del 25 de julio de 2014 del Ministerio de Minas y Energía | I56: TODO LÁMINAS C.E. | J56: Mavill S.A.S. | M56: Alberga los dos medidores de energía de la frontera del proyecto | N56: https://drive.google.com/drive/folders/1aolEGj-F-Yl7o1AgeN3vMol0tvM7HgB8 | P56: P00939
A57: 46 | B57: Cables Solares DC | D57: 11000 | E57: metros | F57: PRYSMIAN GROUP | G57: Cable Fotovoltaico, 6mm2, 1800 V DC, Cobre Suave, Flexible, XLPE | H57: NTC 6404/2020 y la RESOLUCIÓN 90708 de 2013 del MINISTERIO DE MINAS Y ENERGÍA – RETIE (Numeral 20.2) | I57: PRODUCTORA DE CABLES PROCABLES S.A.S. | J57: PRODUCTORA DE CABLES PROCABLES S.A.S. | M57: Transporta la energía DC proveniente de los paneles fotovoltaicos hacia los inversores | N57: https://drive.google.com/drive/folders/1EWcp25cWf4rxmKDGWWA4b7J2Mrcppp9t | P57: P00335
A58: 47 | B58: Cables Solares DC | D58: 11000 | E58: metros | F58: PRYSMIAN GROUP | G58: Cable Fotovoltaico, 6mm2, 1800 V DC, Cobre Suave, Flexible, XLPE | H58: NTC 6404/2020 y la RESOLUCIÓN 90708 de 2013 del MINISTERIO DE MINAS Y ENERGÍA – RETIE (Numeral 20.2) | I58: PRODUCTORA DE CABLES PROCABLES S.A.S. | J58: PRODUCTORA DE CABLES PROCABLES S.A.S. | M58: Transporta la energía DC proveniente de los paneles fotovoltaicos hacia los inversores | N58: https://drive.google.com/drive/folders/1EWcp25cWf4rxmKDGWWA4b7J2Mrcppp9t | P58: P00338
A59: 48 | B59: Alambres y cables en AC | D59: 270 | E59: metros | F59: PROCABLES | G59: Cable de cobre suave 12 AWG 600V THHN/THWN-2 PVC 90°C Seco | H59: NTC 1332/2011, UL 83/2017, ENERSIS/ENDESA E-BT-001/Rev. 6 2011, CODENSA ET-116/2019 y la RESOLUCIÓN 90708 del MINISTERIO DE MINAS Y ENERGÍA – RETIE (Numeral 20.2) | I59: PRODUCTORA DE CABLES PROCABLES S.A.S. | J59: PRODUCTORA DE CABLES PROCABLES S.A.S. | K59: 1746321.6 | L59: =K59*0.19 -> 331801.11 | M59: Conexión de tierra desde los inversores hasta el tablero fotovoltaico | N59: https://drive.google.com/drive/folders/1eQubYT9_KBWjAItKXkUTaLGeGpY3h7BO | P59: P00304
A60: 49 | B60: Alambres y cables en AC | D60: 150 | E60: metros | F60: PROCABLES | G60: Cable termoplástico AA Serie 8000 14 AWG 600V concéntrico THHW PVC 90°C Seco Use CT | H60: NTC 1332/2011, UL 83/2017, ENERSIS/ENDESA E-BT-001/Rev. 6 2011, CODENSA ET-116/2019 y la RESOLUCIÓN 90708 del MINISTERIO DE MINAS Y ENERGÍA – RETIE (Numeral 20.2) | I60: PRODUCTORA DE CABLES PROCABLES S.A.S. | J60: PRODUCTORA DE CABLES PROCABLES S.A.S. | M60: Conexión de tierra desde los inversores hasta el tablero fotovoltaico | N60: https://drive.google.com/drive/folders/1eQubYT9_KBWjAItKXkUTaLGeGpY3h7BO | P60: P00348
A61: 50 | B61: Alambres y cables en AC | D61: 200 | E61: metros | F61: PROCABLES | G61: Cable termoplástico AA Serie 8000 1/0 AWG 600V concéntrico THHW PVC 90°C Seco Use CT | H61: NTC 1332/2011, UL 83/2017, ENERSIS/ENDESA E-BT-001/Rev. 6 2011, CODENSA ET-116/2019 y la RESOLUCIÓN 90708 del MINISTERIO DE MINAS Y ENERGÍA – RETIE (Numeral 20.2) | I61: PRODUCTORA DE CABLES PROCABLES S.A.S. | J61: PRODUCTORA DE CABLES PROCABLES S.A.S. | M61: Transporta la energía AC proveniente de los inversores hasta el tablero fotovoltaico | N61: https://drive.google.com/drive/folders/1eQubYT9_KBWjAItKXkUTaLGeGpY3h7BO | P61: P00280
A62: 51 | B62: Alambres y cables en AC | D62: 300 | E62: metros | F62: PROCABLES | G62: Cobre desnudo suave 1/0 AWG cableado concéntrico clase B | H62: NTC 307/2012, ASTM B3/2013, ASTM B8/2011, ET 121/2013 y la RESOLUCIÓN 90708 de 2013 del MINISTERIO DE MINAS Y ENERGÍA - RETIE (Numeral 20.2) | I62: PRODUCTORA DE CABLES PROCABLES S.A.S. | J62: PRODUCTORA DE CABLES PROCABLES S.A.S. | M62: Componente principal del sistema de puesta a tierra, permite la interconexión de las varillas de puesta a tierra, formando un enmallado | N62: https://drive.google.com/drive/folders/1EgEUg71TCUVyqx5EBRpi-b4OsHDeFAan | P62: P00285
A63: 52 | B63: Alambres y cables en AC | D63: 145 | E63: metros | F63: CENTELSA | G63: Cable THHN/THWN-2 600V 8 AWG | H63: RESOLUCIÓN 40117 DE 02 DE ABRIL DE 2024 DEL MINISTERIO DE MINAS Y ENERGÍA DE COLOMBIA – RETIE, ARTÍCULO 2.3.10 CONDUCTORES Y CABLES ARTÍCULO 2.3.10.3 CABLES AISLADOS DE BAJA TENSIÓN | I63: CABLES DE ENERGÍA Y DE TELECOMUNICACIONES S.A.S | J63: SONEPAR COLOMBIA SAS | K63: 846848.74 | L63: =K63*0.19 -> 160901.26 | M63: Transporta la energía AC proveniente dede el tablero fotovoltaico hasta los servicios auxiliares | N63: https://drive.google.com/drive/folders/1WuTNtriv1hapgWOEIuTbeC9o5UEvD5IR | P63: P04028
A64: 53 | B64: Alambres y cables en AC | D64: 300 | E64: metros | F64: CENTELSA | G64: Cables multiconductores de cobre MULTIFLEX 12 AWG 600V PVC/Nylon 90°C | H64: UL 1277/2018 Rev. 2022 y la RESOLUCIÓN 90708 de 2013 del MINISTERIO DE MINAS Y ENERGÍA –RETIE (Numeral 20.2) | I64: CABLES DE ENERGÍA Y DE TELECOMUNICACIONES S.A.S | J64: SONEPAR COLOMBIA SAS | K64: 2810924.4 | L64: =K64*0.19 -> 534075.63 | M64: Transporta la energía AC proveniente dede el tablero fotovoltaico hasta la estación meteorológica y servicios auxiliares | N64: https://drive.google.com/drive/folders/1zFGe3a4-DbsL2umfuFwyjWh9P2n29sFb | P64: P00288
A65: 54 | B65: Alambres y cables en AC | D65: 300 | E65: metros | F65: PROCABLES | G65: Cobre desnudo suave 2 AWG cableado concéntrico clase B | H65: NTC 1332/2011, UL 83/2017, ENERSIS/ENDESA E-BT-001/Rev. 6 2011, CODENSA ET-116/2019 y la RESOLUCIÓN 90708 del MINISTERIO DE MINAS Y ENERGÍA – RETIE (Numeral 20.2) | I65: PRODUCTORA DE CABLES PROCABLES S.A.S. | J65: PRODUCTORA DE CABLES PROCABLES S.A.S. | M65: Componente principal del sistema de puesta a tierra, permite la interconexión de las varillas de puesta a tierra, formando un enmallado | N65: https://drive.google.com/drive/folders/1EgEUg71TCUVyqx5EBRpi-b4OsHDeFAan | P65: P00283
A66: 55 | B66: Alambres y cables en AC | D66: 120 | E66: metros | F66: CENTELSA | G66: XLPE Al 1/0 AWG 15kV 100% PVC | H66: NTC 2186-2/2015, ICEA S-93-639/2017, NEMA WC 74/2017 y la RESOLUCIÓN 90708 de 2013 del MINISTERIO DE MINAS Y ENERGÍA – RETIE (Numeral 20.2) | I66: CABLES DE ENERGÍA Y DE TELECOMUNICACIONES S.A.S. | J66: SONEPAR | M66: Conexión en media tensión entre la celda de protección y el punto de interconexión a la red del Operador de Red | N66: https://drive.google.com/drive/folders/1fJEhGAAG1s9UUSD3w3L0iQ9ukZ8oTd4Y | P66: P01509
A67: 56 | B67: Alambres y cables en AC | D67: 200 | E67: metros | F67: PROCABLES | G67: Cable termoplástico AA Serie 8000 2 AWG 600V concéntrico THHW PVC 90°C Seco Use CT | H67: NTC 1332/2011, UL 83/2017, ENERSIS/ENDESA E-BT-001/Rev. 6 2011, CODENSA ET-116/2019 y la RESOLUCIÓN 90708 del MINISTERIO DE MINAS Y ENERGÍA – RETIE (Numeral 20.2) | I67: PRODUCTORA DE CABLES PROCABLES S.A.S. | J67: PRODUCTORA DE CABLES PROCABLES S.A.S. | M67: Transporta la energía AC proveniente de los inversores hasta el tablero fotovoltaico | N67: https://drive.google.com/drive/folders/1eQubYT9_KBWjAItKXkUTaLGeGpY3h7BO | P67: P00280
A68: 57 | B68: Alambres y cables en AC | D68: 1000 | E68: metros | F68: CENTELSA | G68: Cable Aluminio 1350 0,6 / 1 kV AC XLPE 90°C PVC | H68: IEC 60502-1 / 2021 (NTC 6074-1 / 2023 para calibres AWG/kcmil) Resolución 40117 De 02 De Abril De 2024 Del Ministerio De Minas Y Energía De Colombia – RETIE, Artículo 2.3.10 Conductores Y Cables, Artículo 2.3.10.3 Cables Aislados De Baja Tensión | I68: CABLES DE ENERGÍA Y DE TELECOMUNICACIONES S.A.S. | J68: SONEPAR | K68: 80960140 | L68: =K68*0.19 -> 15382427 | M68: Transporta la energía AC proveniente de los inversores hasta el tablero fotovoltaico | O68: https://drive.google.com/file/d/1bSJh-OYHclKAlLDpCJWZbB3-hFrInfkN/view?usp=drive_link | P68: P00261
A69: 57 | B69: Alambres y cables en AC | D69: 1000 | E69: metros | F69: PRYSMIAN | G69: Cable de Baja Tensión XZ1 (S) – VOLTENAX/PE 240 mm² Aluminio Compactado 0,6/1 (1,2) kV AC | H69: IEC 60502-1/2021 y la RESOLUCIÓN 90708 de 2013 del MINISTERIO DE MINAS Y ENERGÍA - RETIE (Numeral 20.2) | I69: PRYSMIAN CABOS E SISTEMAS DO BRASIL S/A | J69: PRODUCTORA DE CABLES PROCABLES S.A.S. | K69: 80960140 | L69: =K69*0.19 -> 15382427 | M69: Transporta la energía AC proveniente de los inversores hasta el tablero fotovoltaico | O69: https://drive.google.com/file/d/1pD1XSkGVYvwam9dqzMHD7JR-SgYduRpk/view?usp=drive_link | P69: P00261
A70: 58 | B70: Canalizaciones: canaletas, tubos, prefabricadas con barras o con cables, ductos subterráneos | D70: 3 | E70: metros | F70: INTERFLEX | G70: AGT-17N | H70: Reglamento Técnico de instalaciones eléctricas RETIE . Resolución 90708 de 30 de agosto de 2013, Resolución 90795 de 25 de julio de 2014 del Ministerio de Minas y Energía Numerales 20.6.1 | I70: INTERFLEX S.L | J70: EDEMCO S.A.S. | M70: La tubería se encarga de proteger el cable de conexión de comunicaciones entre el inversor y el Smartlogger | N70: https://drive.google.com/drive/folders/19UyhofeeZK-Q-4qGkg9urPR2kjNeYMOC | P70: No encontrado
A71: 59 | B71: Canalizaciones: canaletas, tubos, prefabricadas con barras o con cables, ductos subterráneos | D71: 6 | E71: Unidades | F71: INTERFLEX | G71: AGT-48N | H71: Reglamento Técnico de instalaciones eléctricas RETIE . Resolución 90708 de 30 de agosto de 2013, Resolución 90795 de 25 de julio de 2014 del Ministerio de Minas y Energía Numerales 20.6.1 | I71: INTERFLEX S.L | J71: EDEMCO S.A.S. | M71: La tubería se encarga de proteger el cable de conexión entre la salida en AC de los inversores y el tablero FV | N71: https://drive.google.com/drive/folders/19UyhofeeZK-Q-4qGkg9urPR2kjNeYMOC | P71: P01048
A72: 60 | B72: Canalizaciones: canaletas, tubos, prefabricadas con barras o con cables, ductos subterráneos | D72: 3 | E72: metros | F72: INTERFLEX | G72: AGT-95N | H72: Reglamento Técnico de instalaciones eléctricas RETIE . Resolución 90708 de 30 de agosto de 2013, Resolución 90795 de 25 de julio de 2014 del Ministerio de Minas y Energía Numerales 20.6.1 | I72: INTERFLEX S.L | J72: EDEMCO S.A.S. | M72: La tubería se encarga de proteger el cable de conexión entre la salida en AC de los inversores y el tablero FV | N72: https://drive.google.com/drive/folders/19UyhofeeZK-Q-4qGkg9urPR2kjNeYMOC | P72: P01047
A73: 61 | B73: Canalizaciones: canaletas, tubos, prefabricadas con barras o con cables, ductos subterráneos | D73: 300 | E73: unidad | F73: PLASTIMEC Y RALCO | G73: TUBOS DE PVC RÍGIDO Conduit Tipo A De 3/4" | H73: NTC 979/2021 y la RESOLUCIÓN 90708 de 2013 del MINISTERIO DE MINAS Y ENERGÍA RETIE (Numeral 20.6) | I73: INDUSTRIA COLOMBIANA DE PLÁSTICOS S.A.S. - IMEC S.A.S. | J73: EDEMCO S.A.S | M73: La tubería se encarga de proteger el cable de comunicación de los inversores con el smartlogger ubicado en la subestación. | N73: https://drive.google.com/drive/folders/1zNd1D2h-z-VYbFcd_0_QKnoePDwbyND- | P73: P01080
A74: 62 | B74: Canalizaciones: canaletas, tubos, prefabricadas con barras o con cables, ductos subterráneos | D74: 160 | E74: unidades | F74: Durman | G74: DUCTOS ELÉCTRICOS Y TELEFÓNICOS DB 3M 2 pulg Referencia 2016200 | H74: NTC 1630 Tubos de PVC para alojar y proteger conductores subterráneos eléctricos y telefónicos Resolución 9 0708 RETIE Accesorios de PVC para Tubería Conduit Cajas de PVC para Instalaciones Eléctricas | I74: Durman by aliaxis | J74: EDEMCO S.A.S | M74: La tubería se encarga de proteger el cable de conexión entre los inversores y el tablero fotovoltaico. | N74: https://drive.google.com/drive/folders/1mapuxMqv4bBnC7lfc-hqPE-GkTStiuHX | P74: P01084
A75: 63 | B75: Canalizaciones: canaletas, tubos, prefabricadas con barras o con cables, ductos subterráneos | D75: 100 | E75: unidades | F75: Durman | G75: DUCTOS ELÉCTRICOS Y TELEFÓNICOS DB 3M 2 pulg referencia 2016201 | H75: "NTC 1630 Tubos de PVC para alojar y proteger conductores subterráneos eléctricos y telefónicos Resolución 9 0708 RETIE Accesorios de PVC para Tubería Conduit Cajas de PVC para Instalaciones Eléctricas" | I75: Durman by aliaxis | J75: EDEMCO S.A.S | M75: La tubería se encarga de proteger el cable de conexión entre los inversores y el tablero fotovoltaico. | N75: https://drive.google.com/drive/folders/1mapuxMqv4bBnC7lfc-hqPE-GkTStiuHX | P75: P01084
A76: 64 | B76: Canalizaciones: canaletas, tubos, prefabricadas con barras o con cables, ductos subterráneos | D76: 800 | E76: unidades | F76: Durman | G76: DUCTOS ELÉCTRICOS Y TELEFÓNICOS DB 3M 2 pulg referencia 2016202 | H76: "NTC 1630 Tubos de PVC para alojar y proteger conductores subterráneos eléctricos y telefónicos Resolución 9 0708 RETIE Accesorios de PVC para Tubería Conduit Cajas de PVC para Instalaciones Eléctricas" | I76: Durman by aliaxis | J76: EDEMCO S.A.S | M76: La tubería se encarga de proteger el cable de conexión entre los inversores y el tablero fotovoltaico. | N76: https://drive.google.com/drive/folders/1mapuxMqv4bBnC7lfc-hqPE-GkTStiuHX | P76: P01084
A77: 65 | B77: Canalizaciones: canaletas, tubos, prefabricadas con barras o con cables, ductos subterráneos | D77: 90 | E77: unidades | F77: Durman | G77: DUCTOS ELÉCTRICOS Y TELEFÓNICOS DB 6M 4 pulg Referencia 2016203 | H77: NTC 1630 Tubos de PVC para alojar y proteger conductores subterráneos eléctricos y telefónicos Resolución 9 0708 RETIE Accesorios de PVC para Tubería Conduit Cajas de PVC para Instalaciones Eléctricas | I77: Durman by aliaxis | J77: EDEMCO S.A.S. | M77: La tubería se encarga de proteger el cable de conexión entre los inversores y el tablero fotovoltaico | N77: https://drive.google.com/drive/folders/1mapuxMqv4bBnC7lfc-hqPE-GkTStiuHX | P77: P01086
A78: 66 | B78: Canalizaciones: canaletas, tubos, prefabricadas con barras o con cables, ductos subterráneos | D78: 50 | E78: unidades | F78: Durman | G78: DUCTOS ELÉCTRICOS Y TELEFÓNICOS DB 6M 6 pulg Referencia 2016204 | H78: NTC 1630 Tubos de PVC para alojar y proteger conductores subterráneos eléctricos y telefónicos Resolución 9 0708 RETIE Accesorios de PVC para Tubería Conduit Cajas de PVC para Instalaciones Eléctricas | I78: Durman by aliaxis | J78: EDEMCO S.A.S. | M78: La tubería se encarga de proteger el cable de conexión entre el transformador y el punto de interconexión del sistema con la red de media tensión | N78: https://drive.google.com/drive/folders/1mapuxMqv4bBnC7lfc-hqPE-GkTStiuHX | P78: No encontrado
A79: 67 | B79: Canalizaciones: canaletas, tubos, prefabricadas con barras o con cables, ductos subterráneos | D79: 40 | E79: unidades | F79: Durman | G79: ADAPTADOR TERMINAL DE CAMPANA PARA DUCTO DB 2 pulg Referencia 9018867 | H79: NTC 1630 Tubos de PVC para alojar y proteger conductores subterráneos eléctricos y telefónicos Resolución 9 0708 RETIE Accesorios de PVC para Tubería Conduit Cajas de PVC para Instalaciones Eléctricas | I79: Durman by aliaxis | J79: SONEPAR COLOMBIA S.A.S | M79: Adaptador terminal para ingreso de tubería a caja de paso | N79: https://drive.google.com/drive/folders/1mapuxMqv4bBnC7lfc-hqPE-GkTStiuHX | P79: No encontrado
A80: 68 | B80: Canalizaciones: canaletas, tubos, prefabricadas con barras o con cables, ductos subterráneos | D80: 30 | E80: unidades | F80: Durman | G80: ADAPTADOR TERMINAL DE CAMPANA PARA DUCTO DB 4 pulg Referencia 9018869 | H80: NTC 1630 Tubos de PVC para alojar y proteger conductores subterráneos eléctricos y telefónicos Resolución 9 0708 RETIE Accesorios de PVC para Tubería Conduit Cajas de PVC para Instalaciones Eléctricas | I80: Durman by aliaxis | J80: Suministros y servicios LG | M80: Adaptador terminal para ingreso de tubería a caja de paso | N80: https://drive.google.com/drive/folders/1mapuxMqv4bBnC7lfc-hqPE-GkTStiuHX | P80: No encontrado
A81: 69 | B81: Canalizaciones: canaletas, tubos, prefabricadas con barras o con cables, ductos subterráneos | D81: 25 | E81: unidades | F81: Durman | G81: ADAPTADOR TERMINAL DE CAMPANA PARA DUCTO DB 6 pulg Referencia 9012947 | H81: NTC 1630 Tubos de PVC para alojar y proteger conductores subterráneos eléctricos y telefónicos Resolución 9 0708 RETIE Accesorios de PVC para Tubería Conduit Cajas de PVC para Instalaciones Eléctricas | I81: Durman by aliaxis | J81: EDEMCO S.A.S. | M81: Adaptador terminal para ingreso de tubería a caja de paso | N81: https://drive.google.com/drive/folders/1mapuxMqv4bBnC7lfc-hqPE-GkTStiuHX | P81: No encontrado
A82: 70 | B82: Canalizaciones: canaletas, tubos, prefabricadas con barras o con cables, ductos subterráneos | E82: unidades | F82: AISCAN | G82: TPI25 - Tubo corrugado ø 25 | H82: IEC 61386-1 de 2008,Numeral 20.6.1 del Reglamento Técnico de Instalaciones Eléctricas - RETIE. Resolución 90708 de 30 de agosto de 2013 del Ministerio de Minas y Energías | I82: AISCAN, S.L. | J82: AISCAN, S.L. | M82: La tubería se encarga de proteger el cable de conexión entre los inversores y el tablero fotovoltaico | O82: https://drive.google.com/file/d/1YJxqQaepEEQ649OUca3H82F8Ekp1SYmq/view?usp=drive_link | P82: P01091
A83: 71 | B83: Canalizaciones: canaletas, tubos, prefabricadas con barras o con cables, ductos subterráneos | E83: unidades | F83: AISCAN | G83: UV63 - Tubo anti UV en rollos ø 63 | H83: IEC 61386-1 de 2008,Numeral 20.6.1 del Reglamento Técnico de Instalaciones Eléctricas - RETIE. Resolución 90708 de 30 de agosto de 2013 del Ministerio de Minas y Energías | I83: AISCAN, S.L. | J83: AISCAN, S.L. | M83: La tubería se encarga de proteger el cable de conexión entre los inversores y el tablero fotovoltaico | O83: https://drive.google.com/file/d/1cvsBxzgGhwkIH3rbQxqN0UMrB0oS8FVD/view?usp=drive_link | P83: P01049
A84: 72 | B84: Canalizaciones: canaletas, tubos, prefabricadas con barras o con cables, ductos subterráneos | E84: unidades | F84: AISCAN | G84: UV110 - Tubo anti UV en rollos ø 110 | H84: IEC 61386-1 de 2008,Numeral 20.6.1 del Reglamento Técnico de Instalaciones Eléctricas - RETIE. Resolución 90708 de 30 de agosto de 2013 del Ministerio de Minas y Energías | I84: AISCAN, S.L. | J84: AISCAN, S.L. | M84: La tubería se encarga de proteger el cable de conexión entre los inversores y el tablero fotovoltaico | O84: https://drive.google.com/file/d/1cvsBxzgGhwkIH3rbQxqN0UMrB0oS8FVD/view?usp=drive_link | P84: P01051
A85: 73 | B85: Canalizaciones: canaletas, tubos, prefabricadas con barras o con cables, ductos subterráneos | E85: unidades | F85: AISCAN | G85: FUV-25 - Tubo curvable FUV ø 25 | H85: IEC 61386-1 de 2008,Numeral 20.6.1 del Reglamento Técnico de Instalaciones Eléctricas - RETIE. Resolución 90708 de 30 de agosto de 2013 del Ministerio de Minas y Energías | I85: AISCAN, S.L. | J85: AISCAN, S.L. | M85: La tubería se encarga de proteger el cable de conexión entre los inversores y el tablero fotovoltaico | O85: https://drive.google.com/file/d/1YJxqQaepEEQ649OUca3H82F8Ekp1SYmq/view?usp=drive_link | P85: P01091
A86: 74 | B86: Canalizaciones: canaletas, tubos, prefabricadas con barras o con cables, ductos subterráneos | E86: unidades | F86: AISCAN | G86: DRN63 - Tubo enterrado normal en rollos ø 63 | H86: IEC 61386-1 de 2008,Numeral 20.6.1 del Reglamento Técnico de Instalaciones Eléctricas - RETIE. Resolución 90708 de 30 de agosto de 2013 del Ministerio de Minas y Energías | I86: AISCAN, S.L. | J86: AISCAN, S.L. | M86: La tubería se encarga de proteger el cable de conexión entre los inversores y el tablero fotovoltaico | O86: https://drive.google.com/file/d/1cvsBxzgGhwkIH3rbQxqN0UMrB0oS8FVD/view?usp=drive_link | P86: P01050
A87: 75 | B87: Canalizaciones: canaletas, tubos, prefabricadas con barras o con cables, ductos subterráneos | E87: unidades | F87: AISCAN | G87: DRN110 - Tubo enterrado normal en rollos ø 110 | H87: IEC 61386-1 de 2008,Numeral 20.6.1 del Reglamento Técnico de Instalaciones Eléctricas - RETIE. Resolución 90708 de 30 de agosto de 2013 del Ministerio de Minas y Energías | I87: AISCAN, S.L. | J87: AISCAN, S.L. | M87: La tubería se encarga de proteger el cable de conexión entre los inversores y el tablero fotovoltaico | O87: https://drive.google.com/file/d/1cvsBxzgGhwkIH3rbQxqN0UMrB0oS8FVD/view?usp=drive_link | P87: P01052
A88: 76 | B88: Bandejas portacables | E88: Metros | F88: AISCAN | G88: Escoger cual o cuales: BMPG, BMPZ, BMPR, BMPI, CMCS, CMPS, CMCG, CMPG, CMCA, CMPA, BEA desde 1010 hasta 660 | H88: IEC 61537:2006; RETIE Resolución 90708 de 2013; Resolución No. 90907 de 2013; Resolución 90795 de 2014. | I88: AISCAN, S.L. | J88: AISCAN, S.L. (si la compra se hace por distribuidor, el proveedor debe tomarse de la oferta/factura comercial). | M88: Soporte de cables en instalaciones eléctricas. | N88: https://drive.google.com/drive/folders/18WAq4KTY-TdgMUjHENyO8NWivHUMqTEy | P88: No encontrado
A89: 77 | B89: Bandejas portacables | D89: 5 | E89: unidades | F89: GALCO | G89: BELG305 | H89: Certificado Retie y Nema en sistemas de conducción eléctrica Certificado de calidad en galvanizado en caliente norma Astm A -123/Astm A 153 DIN 4102-12 ISO 9001: 2015 | I89: GALCO S.A.S | J89: GALCO S.A.S | M89: Estructuras metálicas que sirven para transportar conductores eléctricos desde paneles solares a inversores de manera segura | N89: https://drive.google.com/drive/folders/16DfZviR3HK2rweX-OL9dVN7BhLUkxsmx | P89: P00149
A90: 78 | B90: Bandejas Portacables | D90: 7 | E90: unidades | F90: GALCO | G90: TSEG30 | H90: Certificado Retie y Nema en sistemas de conducción eléctrica Certificado de calidad en galvanizado en caliente norma Astm A -123/Astm A 153 DIN 4102-12 ISO 9001: 2015 | I90: GALCO S.A.S | J90: GALCO S.A.S | M90: Tapas galvanizadas para bandejas portacables. Su función es proveer seguridad a las personas y preservar la vida útil del cableado. | N90: https://drive.google.com/drive/folders/16DfZviR3HK2rweX-OL9dVN7BhLUkxsmx | P90: P00952
A91: 79 | B91: Bandejas Portacables | D91: 10 | E91: unidades | F91: GALCO | G91: CTEC028 | H91: Certificado Retie y Nema en sistemas de conducción eléctrica Certificado de calidad en galvanizado en caliente norma Astm A -123/Astm A 153 DIN 4102-12 ISO 9001: 2015 | I91: GALCO S.A.S | J91: GALCO S.A.S | M91: Chapa de puesta a tierra especial para bandeja enmallada | N91: https://drive.google.com/drive/folders/16DfZviR3HK2rweX-OL9dVN7BhLUkxsmx | P91: P00117
A92: 80 | B92: Bandejas Portacables | D92: 10 | E92: unidades | F92: GALCO | G92: Soporte Peldaño Perfil Dentado | H92: ASTM A123, ASTM A153, ICONTEC 2076 | I92: GALCO S.A.S | J92: GALCO S.A.S | M92: Perfil ranurado utilizado para sujetar la bandeja enmallada a la estructura de los inversores | N92: https://drive.google.com/drive/folders/1k72A9tHRxR4FYo5g4XGyAuGmLdv4Ehbz | P92: P00924
A93: 81 | B93: Canalizaciones: canaletas, tubos, prefabricadas con barras o con cables, ductos subterráneos | D93: 10 | E93: unidades | F93: FUJI | G93: IMC Diámetro 2" | H93: RESOLUCIÓN 90708 de 2013 del MINISTERIO DE MINAS Y ENERGÍA - RETIE (Numeral 20.6) | I93: CUBIERTAS DEL ECUADOR KUBIEC S.A.S | J93: EDEMCO S.A.S. | M93: La tubería se encarga de proteger el cable de tierra que es instalado desde el DPS polimérico instalado en poste hasta la varilla de puesta a tierra | N93: https://drive.google.com/drive/folders/1zltBsmz7UT_9bFiuYPX3SOcyXyvmfjUO | P93: P01076
A94: 82 | B94: Canalizaciones: canaletas, tubos, prefabricadas con barras o con cables, ductos subterráneos | D94: 10 | E94: unidades | F94: FUJI | G94: IMC Diámetro 3/4" | H94: RESOLUCIÓN 90708 de 2013 del MINISTERIO DE MINAS Y ENERGÍA - RETIE (Numeral 20.6) | I94: CUBIERTAS DEL ECUADOR KUBIEC S.A.S | J94: EDEMCO S.A.S. | M94: La tubería se encarga de proteger el cable de tierra que es instalado desde el DPS polimérico instalado en poste hasta la varilla de puesta a tierra | N94: https://drive.google.com/drive/folders/1zltBsmz7UT_9bFiuYPX3SOcyXyvmfjUO | P94: P01072
A95: 83 | B95: Canalizaciones: canaletas, tubos, prefabricadas con barras o con cables, ductos subterráneos | D95: 25 | E95: unidades | F95: FUJI | G95: IMC Diámetro 4" | H95: RESOLUCIÓN 90708 de 2013 del MINISTERIO DE MINAS Y ENERGÍA - RETIE (Numeral 20.6) | I95: CUBIERTAS DEL ECUADOR KUBIEC S.A.S | J95: EDEMCO S.A.S. | M95: La tubería se encarga de proteger el cableado AC en media tensión que es instalado desde la celda de protección hasta el punto de interconexión a la red del Operador de Red | N95: https://drive.google.com/drive/folders/1zltBsmz7UT_9bFiuYPX3SOcyXyvmfjUO | P95: P01078
A96: 85 | B96: Elementos o equipos para el sistema de puesta a tierra (varillas, mallas, grapas, conectores) | D96: 10 | E96: Unidades | F96: COBRES DE COLOMBIA S.A.S. | G96: Varilla maciza de cobre para puesta a tierra, diámetro 14.28 mm, longitud 2.40 m, conforme a referencia CC-E (12.7 a 25.4 mm x 2.40 m a 3.05 m) | H96: NTC 2206/2001 y Resolución 90708 de 2013 (RETIE, numeral 15.3) | I96: COBRES DE COLOMBIA S.A.S. | J96: COBRES DE COLOMBIA S.A.S. | M96: Componente principal del sistema de puesta a tierra, permite la interconexión de las varillas de puesta a tierra, formando un enmallado | N96: https://drive.google.com/drive/folders/17k0D3Iq77oQe-UuiCTdFj3qmrrBOhjpT | P96: P01118
A97: 86 | B97: Elementos o equipos para el sistema de puesta a tierra (varillas, mallas, grapas, conectores) | D97: 2 | E97: unidades | F97: TECNOWELD | G97: SG1TN 505 | H97: UL E359848 | I97: TECNOWELD | J97: EDEMCO S.A.S. | M97: Elemento necesario para unir las derivaciones del sistema de puesta a tierra y para crear el enmallado | N97: https://drive.google.com/drive/folders/1pk3Chg0WPdSs3zFuvtOAq2cZq7GmCGiH | P97: P00722
A98: 87 | B98: Elementos o equipos para el sistema de puesta a tierra (varillas, mallas, grapas, conectores) | D98: 1 | E98: unidades | F98: TECNOWELD | G98: SG1TN 6519 | H98: UL E359848 | I98: TECNOWELD | J98: SONEPAR | K98: 76211.001 | L98: =K98*0.19 -> 14480.09 | M98: Elemento necesario para unir las derivaciones del sistema de puesta a tierra y para crear el enmallado | N98: https://drive.google.com/drive/folders/1952XiGV0w36dsIiIExLhkqevtMrpHBRI | P98: P00723
A99: 88 | B99: Elementos o equipos para el sistema de puesta a tierra (varillas, mallas, grapas, conectores) | D99: 1 | E99: unidades | F99: TECNOWELD | G99: SG1TN 2694 | H99: UL E359848 | I99: TECNOWELD | J99: SONEPAR | K99: 76211.001 | L99: =K99*0.19 -> 14480.09 | M99: Elemento necesario para unir las derivaciones del sistema de puesta a tierra y para crear el enmallado | N99: https://drive.google.com/drive/folders/1952XiGV0w36dsIiIExLhkqevtMrpHBRI | P99: P01244
A100: 89 | B100: Elementos o equipos para el sistema de puesta a tierra (varillas, mallas, grapas, conectores) | D100: 2 | E100: unidades | F100: TECNOWELD | G100: SG1TN 228* | H100: UL E359848 | I100: TECNOWELD | J100: EDEMCO S.A.S. | M100: Elemento necesario para unir las derivaciones del sistema de puesta a tierra y para crear el enmallado | N100: https://drive.google.com/drive/folders/1952XiGV0w36dsIiIExLhkqevtMrpHBRI | P100: P00728
A101: 90 | B101: Elementos o equipos para el sistema de puesta a tierra (varillas, mallas, grapas, conectores) | D101: 2 | E101: unidades | F101: TECNOWELD | G101: SG1TN 430 | H101: UL E359848 | I101: TECNOWELD | J101: EDEMCO S.A.S. | M101: Elemento necesario para unir las derivaciones del sistema de puesta a tierra y para crear el enmallado | N101: https://drive.google.com/drive/folders/1zM0Rev7y-YlY1Lu-IhgyfZF61zp_12Pg | P101: P00729
A102: 91 | B102: Elementos o equipos para el sistema de puesta a tierra (varillas, mallas, grapas, conectores) | D102: 2 | E102: unidades | F102: TECNOWELD | G102: SG1TN 230 | H102: UL E359848 | I102: TECNOWELD | J102: EDEMCO S.A.S. | M102: Elemento necesario para unir las derivaciones del sistema de puesta a tierra y para crear el enmallado | N102: https://drive.google.com/drive/folders/1tps3gz5TqHg0vAXmzvpr4j8-QrZLp9BC | P102: P00726
A103: 92 | B103: Elementos o equipos para el sistema de puesta a tierra (varillas, mallas, grapas, conectores) | D103: 2 | E103: unidades | F103: TECNOWELD | G103: SG1TN 547 | H103: UL E359848 | I103: TECNOWELD | J103: EDEMCO S.A.S. | M103: Elemento necesario para unir las derivaciones del sistema de puesta a tierra y para crear el enmallado | N103: https://drive.google.com/drive/folders/1Avw32_rbo6CYnhy6rrgWk4I6QwIKCB1N | P103: P00727
A104: 93 | B104: Fusibles y porta fusibles | D104: 4 | E104: unidades | F104: LUHFSER | G104: Tipo K de 65 Amperios para 36 kV - Frecuencia 50-60 Hz | H104: Numeral 20.19 del Reglamento Técnico de Instalaciones Eléctricas - RETIE. Resolución 90708 de 30 de agosto de 2013 del Ministerio de Minas y Energías. IEEE Std C37.41-2016/Cor 1-2017, IEEE Std C37,42-2016, NTC 2132-2006, NTC 2133 2002. | I104: ELÉCTRICOS INTERNACIONAL SAS. | J104: EDEMCO S.A.S. | M104: Corta el paso de corriente cuando se detecta una sobrecarga en el circuito para proteger el transformador y los circuitos ramales | N104: https://drive.google.com/drive/folders/1NtmZ4yB99ueHXrp27z2cSBUmOCh153xK | P104: P01387
A105: 94 | B105: Fusibles y porta fusibles | D105: 3 | E105: unidades | F105: CELSA | G105: CORTACIRCUITOS 27 KV 100A 12 kA IX2712512 | H105: ANSI C37.41 (NTC2132) y ANSI C37.42 (NTC 2133.) | I105: CELSA S.A.S. | J105: EDEMCO S.A.S. | M105: Corta el paso de corriente cuando se detecta una sobrecarga en el circuito | N105: https://drive.google.com/drive/folders/1OPYaLQLL6VZHhXpN15KvOt-I2PiB0Fu0 | P105: P00503
A106: 95 | B106: Dispositivos de protección contra sobretensiones transitorias (DPS), descargadores de rayos, apantallamiento | D106: 27 | E106: unidades | F106: CELSA | G106: DPS C-15 MODELO 58470 | H106: IEC 60099-4 | I106: CELSA S.A.S. | J106: EDEMCO S.A.S. | M106: Protección contra sobretensiones en el punto de interconexión a la línea de media tensión | N106: https://drive.google.com/drive/folders/1bgF94U4rhIaJc_Zw8FBt3IamQ1AVSDqu | P106: P00556
...

Sheet FORMATO 4
C2: FORMATO SOLICITUD DE INCENTIVOS TRIBUTARIOS PARA PROYECTOS DE FNCE EXCLUSIÓN DE IVA, DEDUCCIÓN EN RENTA EXENCIÓN DE ARANCEL Y DEPRECIACIÓN ACELERADA | F2: Código: F-CT-01
F3: Fecha: 10/10/2024
F5: Versión: 03
A11: FORMATO 4 FORMATO DE ESPECIFICACIONES DE SERVICIOS (CAPÍTULO III DE LA LEY 1715 DE 2014)
A12: Ítem | B12: Servicio | C12: Proveedor | D12: Alcance | E12: Valor total en COP (Sin incluir IVA) | F12: Valor IVA en COP
A13: 1 | B13: Asesoría y consultoría técnica | C13: ENEXA | D13: El presente servicio corresponde a la ejecución de Ensayos Pull Out Test (POT), estudio técnico indispensable para la validación de las condiciones geomecánicas del terreno en donde se instalará el sistema fotovoltaico. Este estudio resulta necesario para garantizar la viabilidad estructural del proyecto, dado que permite verificar la capacidad de carga y comportamiento del suelo en el sitio exacto de implantación de los paneles solares. Se realizará el Pull out test proyecto MOMPOX NORTE, ensayos a tracción, compresión y lateral 3 perfiles tipo IPE 180 por 3.5 metros de longitud, y 3 perfiles tipo IPE 200 por 3.5 metros de longitud. Procedimiento a aplicar segun especificaciones técnicas de ZentrackSe Hincarán 6 perfiles, 3 perfiles IPE 180 X 3.5m y 3 perfiles IPE 200 X 3.5m, de estas se escogen (2 UND) para las pruebas saturadas | F13: =E13*0.19 -> 0
A14: 2 | B14: Diseño e ingeniería del sistema | C14: Solenium S.A.S | D14: Medición de curvas IV, Verificación de Voltaje de Circuito Abierto Voc y Corriente de Corto Circuito Isc en mini granja solar MGS 0044, ubicada en Santa cruz del Mompox, Bolivar.
A15: 3 | B15: Diseño e ingeniería del sistema | C15: Solenium S.A.S | D15: NGENIERÍA DEL PROYECTO, INCLUYE: Diagrama unifilar, estudio de resistividad del suelo, estudio de conexión, planos de disposición física de la estructura, inversores, paneles y acometidas, plano de conexión de paneles y demás planos necesarios en la etapa de ingeniería de detalle del proyecto | F15: =E15*0.19 -> 0
A16: 4 | B16: Construcción de obras civiles y estructurales para el montaje del sistema. | C16: Solenium S.A.S | D16: El servicio de hincado corresponde a la instalación de las bases del seguidor solar o tracker sobre el cual se soportarán los paneles solares y se moverán para seguir la trayectoria del sol. | F16: =E16*0.19 -> 0
A17: 5 | B17: Instalación, montaje y puesta en operación del sistema. | C17: Solenium S.A.S | D17: 1.Ensayo VLF en terna de Cables de Media Tensión 2.Prueba de Resistencia de aislamiento en acometidas AC y DC. Este servicio hace parte del comisionamiento, permite verificar el correcto aislamiento de los cables a utilizar en el proyecto. | F17: =E17*0.19 -> 0
A18: 6 | B18: Certificación RETIE | C18: Certeam S.A.S | D18: Certificación de instalaciones eléctricas de acuerdo con el Reglamento Técnico de Instalaciones Eléctricas – RETIE (resolución 90708 de 2013) PROYECTO: MGS-0040 LA CACICA, ubicado en VEREDA GLOBO LA VEGA, VALLEDUPAR, CÉSAR. Certificación RETIE de las instalaciones eléctricas de sistema solar fotovoltaico, alimentadores en DC y AC, Centro de Transformación, Red MT Subterránea hasta punto de conexión o transición aéreasubterránea (donde aplique). Incluye revisión del sistema de puesta a tierra, apantallamiento, servicios auxiliares asociados a la planta, entre otros equipos. | E18: $ 5.300.000,00 | F18: $ 1.007.000,00
A19: 7 | B19: Asesoría y consultoría técnica | C19: Negawatt | D19: VERIFICACION Y CERTIFICACION DE LA FRONTERA DE GENERACIÓN MGS 0040-LA CACICA, UBICADA EN VEREDA GLOBO LA VEGA , ARRIBA DE VALLEDUPAR CESAR, CON PROPOSITOS DE CUMPLIR CON LOS REQUISITOS ESTABLECIDOS EN EL CÓDIGO DE MEDIDA PARA ENTRADA COMERCIAL AL SISTEMA Y CUYOS ALCANCES INCLUYE: CUMPLIMIENTO O NO DE LA RESOLUCION CREG 038 DE 2014, MEDIANTE LA CORROBORACION DE LAS CONFORMIDADES EN LOS SISTEMAS DE MEDICION, COMUNICACIONES, TELEMEDICION HACIA LOS CENTROS DE GESTION DE MEDIDAS, SEGURIDAD INFORMATICA Y DE ACCESO. ESTA VERIFICACION SE HARA UTILIZANDO EL PROCEDIMIENTO SEÑALADO EN LA CIRCULAR 098 DEL 13 DE NOVIEMBRE DE 2014. | E19: $ 4.600.000,00 | F19: $ 87.400.000,00
A20: 8 | B20: Instalación, montaje y puesta en operación del sistema. | C20: Transefi S.A.S. | D20: "Pruebas de Relación de transformación (TTR) y de resistencia de devanados, en la posición del conmutador en que se encuentran, a tres transformadores de las siguientes características: trafo 1.25MVA – 13.8kV/800V, trafo de 1.1kVA – 800V/480V y trafo de SSAA. Estas pruebas permiten asegurar que los transformadores proporcionan la relación de voltaje correcta y funcionen de manera eficiente y segura. Verificar que no se tengan malas condiciones eléctricas que puedan generar una afectación a la red de distribución a la que se van a conectar y asegurarse de que no existen cortos ni errores en las conexiones dentro de los transformadores." | E20: $ 3.800.000,00 | F20: $ 722.000,00
A21: 9 | B21: Instalación, montaje y puesta en operación del sistema. | C21: Quimaldi Instruments S.A.S | D21: Análisis termográfico con dron (Pilotaje + informe). Mediante la inspección termográfica con drones se pueden detectar fallos o puntos calientes existentes en un panel solar a causa de un exceso de calentamiento en una unión, en la misma celda o en el cableado y de no corregirse, llegará a averiar la celda o el cableado. En el peor de los casos, puede derivar en un cortocircuito y sus posibles complicaciones como un incendio. y Termografías en transformadores, tableros, inversores. Permite evaluar el correcto funcionamiento de los tableros eléctricos y equipos y detectar puntos calientes, lo que indica que se está presentando una falla, que está circulando un exceso de corriente por algún motivo y que debe corregirse para que el proyecto opere adecuadamente y no se presenten averías o cortocircuitos. Estos servicios hacen parte del comisionamiento. | E21: $ 5.000.000,00 | F21: $ 950.000,00
A22: 11 | B22: Construcción de obras civiles y estructurales para el montaje del sistema. | C22: Solenium S.A.S. | D22: El servicio de hincado corresponde a la instalación de las bases del seguidor solar o tracker sobre el cual se soportarán los paneles solares y se moverán para seguir la trayectoria del sol. Estas bases o hincas serán instaladas con hincadora hidráulica de 1200 J, mediante la presión controlada y la inserción progresiva en el suelo. | E22: $ 234.300.000,00 | F22: $ 44.517.000,00
A23: 13 | B23: Instalación, montaje y puesta en operación del sistema. | C23: ELECTRO MONTES JY S.A.S | D23: INSTALACIÓN, MONTAJE Y PUESTA EN OPERACIÓN DEL SISTEMA, INCLUYE: Instalación, montaje y puesta en operación de un sistema fotovoltaico de 1320.8 kWp en DC y 990 kW en AC, en el municipio de Valledupar, Cesar. | E23: $ 195.003.000,00 | F23: $ 37.050.570,00
A24: 14
A25: 15
A26: 16
A27: 17
A28: 18
A29: 19
A30: 20
A31: 21
A32: 22
A33: 23
A34: 24
A35: 25
... A80: 70

Sheet Hoja 1
A1: Nombre de proyecto | B1: Capacidad Instalada

Sheet Listas2
B4: Rol Solicitante principal | D4: Rol Solicitante secundario | F4: Recurso Energético - Tipo de FNCE Biomasa | H4: Tecnología - Tipo de FNCE Biomasa | J4: Departamentos
B5: Dueño del proyecto | D5: Entidad Bancaria | F5: Bagazo | H5: Biogás
D6: Instalador | F6: Biogás | H6: Gasificación | J6: AMAZONAS
D7: Importador | F7: Calor Residual | H7: Pirolización | J7: ANTIOQUIA
D8: Otro | F8: Repoblaciones Residuales Energéticas | H8: Cultivos_energéticos | J8: ARAUCA
F9: Residuos Agrícolas (desechos de los cultivos) | H9: Generación_cogeneración | J9: ARCHIPIELAGO DE SAN ANDRES PROVIDENCIA Y SANTA CATALINA
B10: Tipo de Generador | F10: Residuos Pecuarios (excremento de los animales) | J10: ATLANTICO
B11: Autogenerador | D11: Niveles de tensión | F11: Residuos Sólidos Urbanos (orgánicos) | J11: BOGOTA D.C.
B12: Cogenerador | D12: Mayor o igual a 220 kV. | F12: Sistemas de Acopio de Biomasa | J12: BOLÍVAR
B13: Generador | D13: Nivel 4: mayor o igual a 57.5 kV y menor a 220 kV. | F13: Otro | J13: BOYACÁ
D14: Nivel 3: mayor o igual a 30 kV y menor a 57.5 kV. | J14: CALDAS
D15: Nivel 2: mayor o igual a 1 kV y menor a 30 kV. | J15: CAQUETÁ
D16: Nivel 1: menor a 1 kV. | H16: Tecnología - Tipo de FNCE Eólica | J16: CASANARE
H17: Eólica | J17: CAUCA
B18: Tipo de FNCE (Ley 1715 de 2014) | J18: CESAR
B19: Biomasa | D19: Tipo de FNCE | F19: Recurso Energético - Tipo de FNCE Eólica | J19: CHOCÓ
B20: Eólica | D20: Biomasa | F20: Viento | J20: CÓRDOBA
B21: Geotérmica | D21: Eólica | H21: Tecnología - Tipo de FNCE Geotérmica | J21: CUNDINAMARCA
B22: PCH | D22: Geotérmica | H22: Central_de_vapor_seco | J22: GUAINÍA
B23: Solar | D23: PCH | F23: Recurso Energético - Tipo de FNCE Geotérmica | H23: Central_flash | J23: GUAVIARE
D24: Solar | F24: Vapor | H24: Central_de_ciclo_binario | J24: HUILA
J25: LA GUAJIRA
B26: =CONCATENATE("TEC_",'FORMATO 2'!$F$20) -> TEC_Solar | J26: MAGDALENA
B27: =CONCATENATE("REC_",'FORMATO 2'!$F$20) -> REC_Solar | F27: Recurso Energético - Tipo de FNCE PCH | J27: META
D28: Sector | F28: Agua | H28: Tecnología - Tipo de FNCE PCH | J28: NARIÑO
D29: Residencial | H29: Hidráulica | J29: NORTE DE SANTANDER
D30: Industrial | H30: Hidrocinética | J30: PUTUMAYO
D31: Transporte | F31: Recurso Energético - Tipo de FNCE Solar | J31: QUINDIO
D32: Terciario (comercial, público y de servicios) | F32: Sol | J32: RISARALDA
D33: Generación eléctrica | J33: SANTANDER
H34: Tecnología - Tipo de FNCE Solar | J34: SUCRE
F35: Selección | H35: Fotovoltaica | J35: TOLIMA
D36: Unidad de Medida | J36: VALLE DEL CAUCA
F37: X | J37: VAUPÉS
D38: metros | J38: VICHADA
D39: unidad | F39: {='FORMATO 2'!F20:V20} -> Solar | G39: 0 | H39: 0 | I39: 0 | J39: 0 | K39: 0 | L39: 0 | M39: 0 | N39: 0 | O39: 0 | P39: 0 | Q39: 0 | R39: 0 | S39: 0 | T39: 0 | U39: 0 | V39: 0
D40: unidades
D41: Kilogramos
F44: {=IF(G12=Listas!$B$20,tecbio,IF(G12=Listas!$B$21,Listas!H$13:H$14,IF(G12=Listas!$B$22,teceol,IF(G12=Listas!$B$23,tecgeo,IF(G12=Listas!$B$24,tecpch,IF(G12=Listas!$B$25,tecsol,"Seleccionar tipo de tecnología"))))))} -> #NAME?

Sheet Listas
G2: Codigos CIIU
B3: Cumple | G3: 0010 - Asalariado
D4: Preinversión | G4: 0141 - Cria de ganado bovino y bufalino
B5: Cumple | D5: Inversión | G5: 0142- Cría de caballos y otros equinos
B6: No cumple | D6: Operación | G6: 0143- Cría de ovejas y cabras
B7: No aplica | G7: 0144 -Cría de ganado porcino
G8: 0145 -Cría de aves de corra
B9: Resultado | G9: 0149 -Cría de otros animales n.c.p.
D10: SIN | G10: 0150 -Explotación mixta (agrícola y pecuaria)
B11: Favorable | D11: ZNI | G11: 0161 -Actividades de apoyo a la agricultura
B12: Desfavorable | G12: 0162 -Actividades de apoyo a la ganadería
B13: Requiere de información aclaratoria | D13: Si | G13: 0163 -Actividades posteriores a la cosecha
D14: No | G14: 0164 -Tratamiento de semillas para propagación
B15: Cumple | G15: 0170 -Caza ordinaria y mediante trampas y actividades de servicios conexas
G16: 0210 -Silvicultura y otras actividades forestales
B17: Si | G17: 0220- Extracción de madera
B18: No | G18: 0230- Recolección de productos forestales diferentes a la madera
B19: No aplica | G19: 0240- Servicios de apoyo a la silvicultura
G20: 0311- Pesca marítima
G21: 0312- Pesca de agua dulce
G22: 0321- Acuicultura marítima
G23: 0322- Acuicultura de agua dulce
G24: 0510- Extracción de hulla (carbón de piedra)
G25: 0520- Extracción de carbón lignito
G26: 0610- Extracción de petróleo crudo
G27: 0620- Extracción de gas natural
G28: 0710- Extracción de minerales de hierro
G29: 0721- Extracción de minerales de uranio y de torio
G30: 0722- Extracción de oro y otros metales preciosos
G31: 0723- Extracción de minerales de níque
... G483: 9609 - Otras actividades de servicios personales n.c.p.

Sheet Bienes
A1: =CONCATENATE("Bienes_",'FORMATO 2'!$F$20,"_",'FORMATO 2'!$F$23) -> Bienes_Solar_Fotovoltaica
A3: Bienes_Biomasa_Biogás | B3: Bienes_Biomasa_Gasificación | C3: Bienes_Biomasa_Pirolización | D3: Bienes_Biomasa_Cultivos_energéticos | E3: Bienes_Biomasa_Generación_cogeneración | F3: Bienes_Eólica_Eólica | G3: Bienes_Geotérmica_Central_de_vapor_seco | H3: Bienes_Geotérmica_Central_flash | I3: Bienes_Geotérmica_Central_de_ciclo_binario | J3: Bienes_PCH_Hidráulica | K3: Bienes_PCH_Hidrocinética | L3: Bienes_Solar_Fotovoltaica
A4: Biodigestores | B4: Gasificadores | C4: Bunkers (almacenamiento de residuos) | D4: Equipos y componentes para la producción de cultivos energéticos (torre de madereo, skidder, harvester, brazo cargador, carreto cosechador, winche o cabrestante, astillador de madera, tractores, grúas y grapas). | E4: Motores de CI diseñados para operar con biogás o biocombustibles | F4: Equipos LIDAR | G4: Bombas centrífugas, electrosumergibles, de calor geotérmicas | H4: Bombas centrífugas, electrosumergibles, de calor geotérmicas | I4: Bombas centrífugas, electrosumergibles, de calor geotérmicas | J4: Tuberías | K4: Tuberías | L4: Equipos de medición del recurso solar
A5: Digestores y post-digestores | B5: Sistemas de purificación del gas | C5: Trituradoras | D5: Equipos para el sistema de riego y drenaje empleados en el establecimiento de cultivos con propósitos energéticos (tuberías de PVC, CPVC, válvulas, tanques, bombas) | E5: Calderas para operar con biomasa, biogás o sus derivados, asi como equipos para adaptación de calderas para uso con biomasa, biogás o sus derivados | F5: Equipos SODAR | G5: Válvulas | H5: Válvulas | I5: Válvulas | J5: Chimeneas de equilibrio, aliviaderos | K5: Chimeneas de equilibrio, aliviaderos | L5: Seguidores solares
A6: Tanques de almacenamiento. | B6: Turbinas de gas y de vapor | C6: Hornos rotatorios para pirólisis | D6: Equipos para mecanización del terreno y extracción de madera (Subsoladores, rastra, caballoneador, taipa, cortamalezas, sembradora) | E6: Turbinas de condensación para operar con biogás | F6: Torres de medición | G6: Silenciadores | H6: Silenciadores | I6: Silenciadores | J6: Válvulas y compuertas | K6: Válvulas y compuertas | L6: Datalogger
A7: Equipos de medición de producción de biogás y concentración de metano | B7: Generadores de vapor | C7: Cámaras de combustión | D7: Máquinas peletizadoras | E7: Turbinas de contra-presión para operar con biogás | F7: Anemómetros | G7: Desarenadoras | H7: Desarenadoras | I7: Desarenadoras | J7: Turbinas | K7: Turbinas | L7: Estaciones meteorológicas
A8: Equipos para desulfuración de biogás (y remoción de impurezas) | B8: Unidad funcional | C8: Separador magnético | D8: Equipos para la preparación y transformación de biomasa (equipos de torrefacción, secadores de biomasa, maquinas briqueteadoras) | E8: Incineradores de residuos y sus componentes para la recuperación de calor para la tecnología “waste to energy” | F8: Veletas | G8: Tuberías de vapor, salmuera | H8: Tuberías de vapor, salmuera | I8: Tuberías de vapor, salmuera | J8: Turbogeneradores | K8: Turbogeneradores | L8: Unidad funcional
A9: Equipos para remoción de CO2 de biogás (equipos para producción de biometano) | B9: Máquinas peletizadoras | C9: Turbogeneradores | D9: Equipos para el transporte de biomasa (transportadores de tornillo sinfín, elevadores de cangilones, transportadores de cadena Redler, sinfines, transportadores de banda) | E9: Bio-refinerías para transformación de residuos sólidos urbanos en biocombustibles líquidos | F9: Data Logger | G9: Separadores de vapor o de humedad | H9: Separadores de vapor o de humedad | I9: Separadores de vapor o de humedad | J9: Dispositivos de regulación y tubos difusores | K9: Dispositivos de regulación y tubos difusores | L9: Paneles/módulos o celdas fotovoltaicas
A10: Ventiladores / sopladores para flujo de biogás | B10: Equipos para la preparación y transformación de biomasa (equipos de torrefacción, secadores de biomasa, maquinas briqueteadoras) | C10: Calderas | D10: Medidores bidireccionales | E10: Generadores | F10: Estaciones meteorológicas | G10: Tanques de almacenamiento | H10: Tanques de almacenamiento | I10: Tanques de almacenamiento | J10: Bombas y motores | K10: Bombas y motores | L10: Inversores o microinversores (Off Grid, Grid Tie o Híbrido)
A11: Válvulas | B11: Equipos para el transporte de biomasa (transportadores de tornillo sinfín, elevadores de cangilones, transportadores de cadena Redler, sinfines, transportadores de banda) | C11: Filtros de manga | D11: Medidores Inteligentes | E11: Recuperadores de calor | F11: Equipos de alimentación DC/AC | G11: Intercambiadores de calor, evaporadores o condensadores | H11: Intercambiadores de calor, evaporadores o condensadores | I11: Intercambiadores de calor, evaporadores o condensadores | J11: Elementos hidromecánicos | K11: Elementos hidromecánicos | L11: Reguladores o controladores de carga
A12: Trampas: de ácido sulfhídrico, de llama, de agua | B12: Medidores bidireccionales | C12: Catalizadores | D12: Transformadores (de potencia, medida e instrumentación) | E12: Sistemas de pretratamiento de agua | F12: Unidad funcional | G12: Turbinas | H12: Turbinas | I12: Turbinas | J12: Generadores | K12: Generadores | L12: Baterías solares (de ciclo de descarga profunda): Puede ser de plomo-acido, ions de litio, niquel cadmio, u otro.
A13: Calderas | B13: Medidores Inteligentes | C13: Ventiladores | D13: Bóvedas, puertas cortafuego, compuertas de ventilación y sellos cortafuego | E13: Sistemas de tratamiento de gases de chimenea de las calderas | F13: Aerogeneradores (como un todo) | G13: Generadores | H13: Generadores | I13: Generadores | J13: Transformadores de excitación y rectificadores | K13: Transformadores de excitación y rectificadores | L13: Optimizadores
A14: Hornos | B14: Transformadores (de potencia, medida e instrumentación) | C14: Unidad funcional | D14: Celdas AC/DC | E14: Sistemas recuperadores de condensados | F14: Torres de aerogeneradores | G14: Instrumentos de medida de presión (manómetro), temperatura y flujo másico de fluidos y vapor | H14: Instrumentos de medida de presión (manómetro), temperatura y flujo másico de fluidos y vapor | I14: Instrumentos de medida de presión (manómetro), temperatura y flujo másico de fluidos y vapor | J14: Equipos de regulación de tensión, equipo de regulación de velocidad, control, protección y medida | K14: Equipos de regulación de tensión, equipo de regulación de velocidad, control, protección y medida | L14: Bases / marcos / estructuras diseñadas para montar, anclar e instalar paneles
... A30: Alambres y cables en AC | B30: Equipos de monitoreo, control y automatización (no incluye equipos para conexión a internet) | C30: Fusibles y portafusibles | D30: BESS (Sistema de almacenamiento con base en baterías) | E30: Medidores bidireccionales | F30: Interruptores, reconectadores, seccionadores y transferencias automáticas | G30: Instalaciones superficiales para prueba de pozos | H30: Instalaciones superficiales para prueba de pozos | I30: Instalaciones superficiales para prueba de pozos | J30: Interruptores, reconectadores, seccionadores y transferencias automáticas | K30: Interruptores, reconectadores, seccionadores y transferencias automáticas | L30: Canalizaciones: canaletas, tubos, prefabricadas con barras o con cables, ductos subterráneos
A31: Canalizaciones: canaletas, tubos, prefabricadas con barras o con cables, ductos subterráneos | B31: Subestación o Power Station (transformadores, interruptores, seccionadores, trampas de onda, reconectadores, cuchillas, descargadores de sobretensión) | C31: Interruptores, reconectadores, seccionadores y transferencias automáticas | E31: Medidores Inteligentes | F31: Interruptores de baja tensión | G31: Medidores bidireccionales | H31: Medidores bidireccionales | I31: Medidores bidireccionales | J31: Interruptores de baja tensión | K31: Interruptores de baja tensión | L31: Bandejas portacables
A32: Bandejas portacables | B32: BESS (Sistema de almacenamiento con base en baterías) | C32: Interruptores de baja tensión | E32: Transformadores (de potencia, medida e instrumentación) | F32: Dispositivos de protección contra sobretensiones transitorias (DPS), descargadores de rayos, apantallamiento | G32: Medidores Inteligentes | H32: Medidores Inteligentes | I32: Medidores Inteligentes | J32: Dispositivos de protección contra sobretensiones transitorias (DPS), descargadores de rayos, apantallamiento | K32: Dispositivos de protección contra sobretensiones transitorias (DPS), descargadores de rayos, apantallamiento | L32: Barrajes
A33: Barrajes | C33: Dispositivos de protección contra sobretensiones transitorias (DPS), descargadores de rayos, apantallamiento | E33: Bóvedas, puertas cortafuego, compuertas de ventilación y sellos cortafuego | F33: Unidades de potencia ininterrumpida (UPS) | G33: Transformadores (de potencia, medida e instrumentación) | H33: Transformadores (de potencia, medida e instrumentación) | I33: Transformadores (de potencia, medida e instrumentación) | J33: Unidades de potencia ininterrumpida (UPS) | K33: Unidades de potencia ininterrumpida (UPS) | L33: Cajas y conduletas
A34: Cajas y conduletas | C34: Unidades de potencia ininterrumpida (UPS) | E34: Celdas AC/DC | F34: Elementos o equipos para el sistema de puesta a tierra (varillas, mallas, grapas, conectores) | G34: Bóvedas, puertas cortafuego, compuertas de ventilación y sellos cortafuego | H34: Bóvedas, puertas cortafuego, compuertas de ventilación y sellos cortafuego | I34: Bóvedas, puertas cortafuego, compuertas de ventilación y sellos cortafuego | J34: Elementos o equipos para el sistema de puesta a tierra (varillas, mallas, grapas, conectores) | K34: Elementos o equipos para el sistema de puesta a tierra (varillas, mallas, grapas, conectores) | L34: Fusibles y porta fusibles
A35: Fusibles y portafusibles | C35: Elementos o equipos para el sistema de puesta a tierra (varillas, mallas, grapas, conectores) | E35: Contadores | F35: Sistema de monitoreo, control y automatización | G35: Celdas AC/DC | H35: Celdas AC/DC | I35: Celdas AC/DC | J35: Sistema de monitoreo, control y automatización | K35: Sistema de monitoreo, control y automatización | L35: Interruptores, reconectadores, seccionadores y transferencias automáticas
A36: Interruptores, reconectadores, seccionadores y transferencias automáticas | C36: Equipos de monitoreo, control y automatización (no incluye equipos para conexión a internet) | E36: Tableros de baja tensión AC/DC (Incluye los elementos internos) | F36: Subestación o Power Station | G36: Contadores | H36: Contadores | I36: Contadores | J36: Subestación o Power Station | K36: Subestación o Power Station | L36: Interruptores de baja tensión
A37: Interruptores de baja tensión | C37: Subestación o Power Station (transformadores, interruptores, seccionadores, trampas de onda, reconectadores, cuchillas, descargadores de sobretensión) | E37: Alambres y cables en AC | F37: BESS (Sistema de almacenamiento con base en baterías) | G37: Tableros de baja tensión AC/DC (Incluye los elementos internos) | H37: Tableros de baja tensión AC/DC (Incluye los elementos internos) | I37: Tableros de baja tensión AC/DC (Incluye los elementos internos) | J37: BESS (Sistema de almacenamiento con base en baterías) | K37: BESS (Sistema de almacenamiento con base en baterías) | L37: Dispositivos de protección contra sobretensiones transitorias (DPS), descargadores de rayos, apantallamiento
A38: Dispositivos de protección contra sobretensiones transitorias (DPS), descargadores de rayos, apantallamiento | C38: BESS (Sistema de almacenamiento con base en baterías) | E38: Canalizaciones: canaletas, tubos, prefabricadas con barras o con cables, ductos subterráneos | G38: Alambres y cables en AC | H38: Alambres y cables en AC | I38: Alambres y cables en AC | L38: Unidades de potencia ininterrumpida (UPS)
A39: Unidades de potencia ininterrumpida (UPS) | C39: Sistemas de acopio de biomasa | E39: Bandejas portacables | G39: Canalizaciones: canaletas, tubos, prefabricadas con barras o con cables, ductos subterráneos | H39: Canalizaciones: canaletas, tubos, prefabricadas con barras o con cables, ductos subterráneos | I39: Canalizaciones: canaletas, tubos, prefabricadas con barras o con cables, ductos subterráneos | L39: Elementos o equipos para el sistema de puesta a tierra (varillas, mallas, grapas, conectores)
A40: Elementos o equipos para el sistema de puesta a tierra (varillas, mallas, grapas, conectores) | E40: Barrajes | G40: Bandejas portacables | H40: Bandejas portacables | I40: Bandejas portacables | L40: Sistema de monitoreo, control y automatización
A41: Equipos de monitoreo, control y automatización (no incluye equipos para conexión a internet) | E41: Cajas y conduletas | G41: Barrajes | H41: Barrajes | I41: Barrajes | L41: Subestación o Power Station
A42: Subestación o Power Station (transformadores, interruptores, seccionadores, trampas de onda, reconectadores, cuchillas, descargadores de sobretensión) | E42: Fusibles y portafusibles | G42: Cajas y conduletas | H42: Cajas y conduletas | I42: Cajas y conduletas | L42: BESS (Sistema de almacenamiento con base en baterías)
A43: BESS (Sistema de almacenamiento con base en baterías) | E43: Interruptores, reconectadores, seccionadores y transferencias automáticas | G43: Fusibles y porta fusibles | H43: Fusibles y porta fusibles | I43: Fusibles y porta fusibles
E44: Interruptores de baja tensión | G44: Interruptores, reconectadores, seccionadores y transferencias automáticas | H44: Interruptores, reconectadores, seccionadores y transferencias automáticas | I44: Interruptores, reconectadores, seccionadores y transferencias automáticas
E45: Dispositivos de protección contra sobretensiones transitorias (DPS), descargadores de rayos, apantallamiento | G45: Interruptores de baja tensión | H45: Interruptores de baja tensión | I45: Interruptores de baja tensión
E46: Unidades de potencia ininterrumpida (UPS) | G46: Dispositivos de protección contra sobretensiones transitorias (DPS), descargadores de rayos, apantallamiento | H46: Dispositivos de protección contra sobretensiones transitorias (DPS), descargadores de rayos, apantallamiento | I46: Dispositivos de protección contra sobretensiones transitorias (DPS), descargadores de rayos, apantallamiento
E47: Elementos o equipos para el sistema de puesta a tierra (varillas, mallas, grapas, conectores) | G47: Unidades de potencia ininterrumpida (UPS) | H47: Unidades de potencia ininterrumpida (UPS) | I47: Unidades de potencia ininterrumpida (UPS)
E48: Equipos de monitoreo, control y automatización (no incluye equipos para conexión a internet) | G48: Elementos o equipos para el sistema de puesta a tierra (varillas, mallas, grapas, conectores) | H48: Elementos o equipos para el sistema de puesta a tierra (varillas, mallas, grapas, conectores) | I48: Elementos o equipos para el sistema de puesta a tierra (varillas, mallas, grapas, conectores)
E49: Subestación o Power Station (transformadores, interruptores, seccionadores, trampas de onda, reconectadores, cuchillas, descargadores de sobretensión) | G49: Sistema de monitoreo, control y automatización | H49: Sistema de monitoreo, control y automatización | I49: Sistema de monitoreo, control y automatización
E50: BESS (Sistema de almacenamiento con base en baterías) | G50: Subestación o Power Station | H50: Subestación o Power Station | I50: Subestación o Power Station
E51: Grupo Electrógeno de Biogás | G51: BESS (Sistema de almacenamiento con base en baterías) | H51: BESS (Sistema de almacenamiento con base en baterías) | I51: BESS (Sistema de almacenamiento con base en baterías)

Sheet Servicios
A1: =CONCATENATE("Servicios_",'FORMATO 2'!$F$20,"") -> Servicios_Solar
A3: Servicios_Biomasa | B3: Servicios_Eólica | C3: Servicios_Geotérmica | D3: Servicios_PCH | E3: Servicios_Solar
A4: Estudios de valoración de potencial para uso energético de la biomasa | B4: Estudios de valoración de potencial del recurso eólico. | C4: Alquiler equipos y plataformas de perforación para exploración geotérmica y pruebas de producción de pozos geotérmicos | D4: Estudios de valoración de potencial hidráulico | E4: Estudios de valoración de potencial del recurso solar
A5: Estudios ambientales | B5: Estudios ambientales | C5: Toma de fotografías aéreas; imágenes de satélite; etc para elaboración de cartografía | D5: Estudios ambientales | E5: Estudios ambientales
A6: Estudios de conexión. | B6: Estudios de conexión | C6: Estudios de valoración de potencial del recurso geotérmico | D6: Estudios de conexión | E6: Estudios de conexión
A7: Asesoría y consultoría técnica | B7: Asesoría y consultoría técnica | C7: Estudios ambientales | D7: Asesoría y consultoría técnica | E7: Estudios estructurales
A8: Diseño e Ingeniería del sistema | B8: Diseño e Ingeniería del sistema | C8: Estudios de gradiente térmico | D8: Diseño e Ingeniería del sistema | E8: Asesoría y consultoría técnica
A9: Transporte asociado al traslado de componentes al sitio de instalación | B9: Transporte asociado al traslado de componentes al sitio de instalación | C9: Estudios de conexión. | D9: Transporte asociado al traslado de componentes al sitio de instalación | E9: Diseño e ingeniería del sistema
A10: Instalación, montaje y puesta en operación del sistema. | B10: Instalación, montaje y puesta en operación del sistema. | C10: Geología / exploración. Recolección de muestras de roca y ensayos de laboratorio | D10: Instalación, montaje y puesta en operación del sistema. | E10: Transporte asociado al traslado de componentes al sitio de instalación
A11: Construcción de obras civiles y estructurales para el montaje del sistema. | B11: Construcción de obras civiles y estructurales para el montaje del sistema. | C11: Geoquímica / exploración. Recolección de muestras de líquidos y gases y ensayos de laboratorio para análisis de composición química; análisis de isótopos. | D11: Construcción de obras civiles y estructurales para el montaje del sistema. | E11: Instalación, montaje y puesta en operación del sistema.
A12: Preparación / adaptación del terreno para instalación del sistema | B12: Obras civiles y estructurales para efectos de medición del recurso eólico | C12: Geofísica / exploración. Muestreo; procesamiento y análisis de gravimetría; magnetometría; magnetotelúrica y microsismos) | D12: Preparación / adaptación del terreno para instalación del sistema | E12: Construcción de obras civiles y estructurales para el montaje del sistema.
A13: Construcción de digestores; post-digestores y tanques de almacenamiento para proyectos de uso energético de la biomasa | B13: Preparación / adaptación del terreno para instalación del sistema | C13: Asesoría y consultoría técnica | E13: Preparación / adaptación del terreno para instalación del sistema
A14: Construcción de lagunas para proyectos de uso energético de la biomasa | C14: Diseño e Ingeniería del sistema (Incluyendo software especializado) | E14: Certificación RETIE
A15: Construcción de instalaciones de recibo y acopio de biomasa para ser usada con fines energéticos | C15: Instalación, montaje y puesta en operación del sistema.
C16: Construcción de obras civiles y estructurales para el montaje del sistema.
C17: Preparación / adaptación del terreno para instalación del sistema
C18: Transporte asociado al traslado de componentes al sitio de instalación

Sheet Items BT Faltantes
A1: ITEMS MARCADOS COMO "BT" EN PEPC QUE FALTAN EN EL FORMATO 3 DEL "PAPÁ DE LOS FORMATOS"
A2: Estos elementos aparecen marcados con "BT" en la columna BT de la hoja PEPC pero no están registrados en el FORMATO 3 (ni por código Odoo ni por descripción equivalente). Se excluyen servicios (transporte, nacionalización, instalación, pruebas, etc.).
A4: # | B4: Código Odoo | C4: Descripción (de PEPC) | D4: Unidad | E4: Cantidad | F4: Nombre canónico Odoo (si código existe)
A5: 1 | B5: P01036 | C5: Transformador de potencia 17.5kV 13.2/120 500VA | D5: Und | E5: 1 | F5: Nombre Odoo: [P01036] Transformador Potencia 1500 kVA Dyn5 13200/800 V
A6: 2 | B6: P00609 | C6: Gabinete, 2 borneras, 2 modem telemedida | D6: Und | E6: 1 | F6: Nombre Odoo: [P00609] Gabinete
A7: 3 | B7: P00364 | C7: Suministro cable XLPE 1/0 Pantalla en hilo 100% Aluminio 15kV (x3 terna) | D7: m | E7: 15 | F7: Nombre Odoo: [P00364] Cable XLPE Pantalla en Cinta (35 KV, 1/0 AWG) - 35 KV / 1/0 AWG
A8: 4 | B8: P00320 | C8: Suministro cable ecológico ASCR | D8: m | E8: 445 | F8: Nombre Odoo: [P00320] Cable Ecológico ASCR (15 KV, 1/0 AWG) - 15 KV / 1/0 AWG
A9: 5 | B9: P00572 | C9: Estación meteorológica | D9: Und | E9: 1 | F9: Nombre Odoo: [P00572] Estación Metereológica
A10: 6 | B10: Sin código | C10: CABLE 500 kcmil Al RHW 800V (Fases inversores 249 kW - Tablero FV) | D10: m | E10: 2000
A11: 7 | B11: Sin código | C11: CABLE 12 AWG Cu 600V (SSAA) | D11: m | E11: 300
A12: 8 | B12: Sin código | C12: Par hembra y macho de MC4 | D12: Und | E12: 200
A13: 9 | B13: Sin código | C13: Tubo PVC DB Liso 4" x 6M | D13: Und | E13: 400
A14: 10 | B14: Sin código | C14: Tubo EMT 3/4" x 6m | D14: Und | E14: 6
A15: 11 | B15: Sin código | C15: Tubo anillado de poliamida Interflex Nylofix AGT-12N (paq x 30m) | D15: Und | E15: 8
A16: 12 | B16: Sin código | C16: Tubo PVC BD Liso 1/2" x 3m | D16: Und | E16: 100
A17: 13 | B17: Sin código | C17: Coraza Americana 1" | D17: m | E17: 10
A18: 14 | B18: Sin código | C18: Puntas captadoras de apantallamiento | D18: Und | E18: 4
